Workbook

Sheet 說明
A1: 世界島社區財報整理
A3: 資料期間 | B3: 2021-01 ~ 2026-04 (63 個月)
A4: 帳戶數 | B4: 8 個（跨期合併）
A5: 分類規則來源 | B5: build_world_island_html.py 內 JS regex
A6: 分類大類 | B6: 收入 8 類、支出 12 類
A8: Sheet 1 月度摘要 | B8: 每月收入/支出/結餘總額、帳戶期末總餘額、專款餘額
A9: Sheet 2 收入分類矩陣 | B9: rows=月份, cols=收入分類, values=金額（pivot 表）
A10: Sheet 3 支出分類矩陣 | B10: rows=月份, cols=支出分類, values=金額
A11: Sheet 4 收入明細 | B11: 每筆收入逐項列出，最後一欄為分類結果；其他收入用黃色高亮
A12: Sheet 5 支出明細 | B12: 每筆支出逐項列出，columns: 月份/顯示名稱/金額/分類/Section/議案類別 — 議案類別 column 黃=外牆修繕、藍=納管、橙=電梯
A13: Sheet 6 議案-外牆修繕 | B13: PPT 第 4 頁 data source — SUMIFS 自動從支出明細抓合計
A14: Sheet 7 議案-納管 | B14: 同上，SUMIFS 條件為「納管」
A15: Sheet 8 議案-電梯 | B15: 同上，SUMIFS 條件為「電梯」(崇友月保養 + 各種修繕/零件，排除撥補)
... A24: 議案驗證 | B24: Sheet 6/7 的「合計金額」(B5 SUMIFS 公式) 應 = 「明細加總」(底部 SUM 公式)，差額應為 0
A26: ⚠️ 私人資料 — 僅可於 Google Drive 私人路徑保存，不可進入 git repo 或 public demo

Sheet 月度摘要
A1: 月份 | B1: 收入合計 | C1: 支出合計 | D1: 結餘 | E1: 結餘率 | F1: 帳戶期末總餘額 | G1: 充電樁專款餘額 | H1: 電梯專款餘額 | I1: 暫收款活動筆數 | J1: 收入項目數 | K1: 支出項目數
A2: 2021-01 | B2: 2179294 | C2: 1224893 | D2: 954401 | E2: 0.43794045 | F2: 19202835 | G2: 0 | H2: 0 | I2: 0 | J2: 11 | K2: 30
A3: 2021-02 | B3: 889634 | C3: 1583724 | D3: -694090 | E3: -0.78019725 | F3: 17372468 | G3: 0 | H3: 0 | I3: 8 | J3: 12 | K3: 29
A4: 2021-03 | B4: 98149 | C4: 1277874 | D4: -1179725 | E4: -12.019735 | F4: 16266550 | G4: 0 | H4: 0 | I4: 0 | J4: 12 | K4: 34
A5: 2021-04 | B5: 2315258 | C5: 984380 | D5: 1330878 | E5: 0.57482924 | F5: 17671352 | G5: 0 | H5: 0 | I5: 0 | J5: 10 | K5: 24
A6: 2021-05 | B6: 507549 | C6: 1124613 | D6: -617064 | E6: -1.2157723 | F6: 17148173 | G6: 0 | H6: 0 | I6: 0 | J6: 10 | K6: 30
A7: 2021-06 | B7: 121511 | C7: 1289875 | D7: -1168364 | E7: -9.6152941 | F7: 15954141 | G7: 0 | H7: 0 | I7: 0 | J7: 11 | K7: 31
A8: 2021-07 | B8: 2650284 | C8: 1324208 | D8: 1326076 | E8: 0.50035242 | F8: 17334102 | G8: 0 | H8: 0 | I8: 0 | J8: 14 | K8: 28
A9: 2021-08 | B9: 507211 | C9: 985197 | D9: -477986 | E9: -0.94238098 | F9: 16954040 | G9: 0 | H9: 0 | I9: 0 | J9: 10 | K9: 28
A10: 2021-09 | B10: 80847 | C10: 1673787 | D10: -1592940 | E10: -19.703143 | F10: 15455024 | G10: 0 | H10: 0 | I10: 0 | J10: 10 | K10: 26
A11: 2021-10 | B11: 2373545 | C11: 1119183 | D11: 1254362 | E11: 0.52847618 | F11: 16743271 | G11: 0 | H11: 0 | I11: 0 | J11: 11 | K11: 28
A12: 2021-11 | B12: 618604 | C12: 1619709 | D12: -1001105 | E12: -1.6183293 | F12: 15716090 | G12: 0 | H12: 0 | I12: 0 | J12: 10 | K12: 30
A13: 2021-12 | B13: 199141 | C13: 1114396 | D13: -915255 | E13: -4.5960149 | F13: 14855149 | G13: 0 | H13: 0 | I13: 0 | J13: 10 | K13: 26
... A65: 2026-04 | B65: 5499534 | C65: 2703526 | D65: 2796008 | E65: 0.50840817 | F65: 11623750 | G65: 1865135 | H65: 0 | I65: 4 | J65: 11 | K65: 38
A66: 全期合計 | B66: 90252406 | C66: 91292894 | D66: -1040488 | E66: -0.011528646

Sheet 支出分類矩陣
A1: 月份 | B1: 管理服務費 | C1: 保全服務費 | D1: 清潔服務費 | E1: 電梯保養與修繕 | F1: 機電/消防/弱電/AED | G1: 公共水電瓦斯 | H1: 電話/網路費 | I1: 垃圾廢棄物/園藝 | J1: 工程維修/購置 | K1: 行政/會議/律師 | L1: 內部轉帳 | M1: 其他支出 | N1: 合計
A2: 2021-01 | D2: 199550 | E2: 101050 | F2: 48950 | G2: 87413 | H2: 4978 | I2: 95705 | K2: 46000 | L2: 134077 | M2: 507170 | N2: 1224893
A3: 2021-02 | D3: 209900 | E3: 100000 | F3: 741328 | I3: 52990 | K3: 8000 | L3: 4541 | M3: 374920 | N3: 1491679
A4: 2021-03 | D4: 198000 | E4: 149770 | F4: 95276 | G4: 101777 | H4: 10400 | I4: 52990 | J4: 52650 | K4: 36512 | L4: 66434 | M4: 514065 | N4: 1277874
A5: 2021-04 | D5: 200730 | E5: 100000 | F5: 54132 | G5: 89691 | H5: 5221 | I5: 93700 | L5: 63606 | M5: 377300 | N5: 984380
A6: 2021-05 | D6: 199220 | E6: 146305 | F6: 70160 | G6: 84824 | H6: 4858 | I6: 58000 | J6: 83100 | L6: 71296 | M6: 406850 | N6: 1124613
A7: 2021-06 | D7: 210880 | E7: 195500 | F7: 117350 | G7: 92524 | H7: 5275 | I7: 175280 | J7: 49500 | L7: 75466 | M7: 368100 | N7: 1289875
A8: 2021-07 | D8: 202990 | E8: 115750 | F8: 346855 | G8: 89266 | H8: 4897 | I8: 66500 | K8: 25000 | L8: 66615 | M8: 406335 | N8: 1324208
A9: 2021-08 | D9: 201280 | E9: 104620 | F9: 62550 | G9: 103421 | H9: 5130 | I9: 73700 | L9: 63596 | M9: 370900 | N9: 985197
A10: 2021-09 | D10: 201570 | E10: 105800 | F10: 97750 | G10: 80066 | H10: 5314 | I10: 64840 | J10: 685000 | L10: 63877 | M10: 369570 | N10: 1673787
A11: 2021-10 | D11: 206663 | E11: 100000 | F11: 143490 | G11: 105471 | H11: 5161 | I11: 58000 | J11: 31500 | L11: 64588 | M11: 404310 | N11: 1119183
A12: 2021-11 | D12: 200678 | E12: 117000 | F12: 595100 | G12: 104138 | H12: 5226 | I12: 79780 | J12: 4934 | L12: 63453 | M12: 449400 | N12: 1619709
A13: 2021-12 | D13: 202208 | E13: 123560 | F13: 165668 | G13: 79194 | H13: 4870 | I13: 58000 | J13: 35800 | L13: 65696 | M13: 379400 | N13: 1114396
A14: 2022-01 | D14: 203069 | E14: 100000 | F14: 256220 | G14: 82554 | H14: 5037 | I14: 81200 | J14: 102010 | L14: 63356 | M14: 387400 | N14: 1280846
A15: 2022-02 | D15: 207374 | E15: 134800 | F15: 99010 | G15: 99540 | I15: 67300 | J15: 31500 | L15: 73714 | M15: 384900 | N15: 1098138
A16: 2022-03 | D16: 201945 | E16: 100000 | F16: 113300 | G16: 97724 | H16: 9748 | I16: 81265 | J16: 22500 | K16: 52000 | L16: 74889 | M16: 479400 | N16: 1232771
A17: 2022-04 | D17: 203174 | E17: 136560 | F17: 165750 | G17: 90017 | H17: 5118 | I17: 62400 | L17: 62822 | M17: 398907 | N17: 1124748
A18: 2022-05 | D18: 201000 | E18: 142000 | F18: 91070 | G18: 89633 | H18: 5008 | I18: 84075 | J18: 27150 | L18: 61970 | M18: 379400 | N18: 1081306
A19: 2022-06 | D19: 203930 | E19: 100000 | F19: 48950 | G19: 92053 | H19: 4864 | I19: 67800 | J19: 22800 | L19: 69484 | M19: 396533 | N19: 1006414
A20: 2022-07 | D20: 201000 | E20: 100000 | F20: 48950 | G20: 101869 | H20: 4903 | I20: 66600 | J20: 101950 | L20: 70395 | M20: 383900 | N20: 1079567
A21: 2022-08 | D21: 204885 | E21: 111235 | F21: 48950 | G21: 113741 | H21: 4851 | I21: 86625 | J21: 29900 | K21: 25000 | L21: 60740 | M21: 385827 | N21: 1071754
A22: 2022-09 | D22: 201000 | E22: 130765 | F22: 48950 | G22: 114022 | H22: 5149 | I22: 64800 | J22: 22660 | L22: 69202 | M22: 390900 | N22: 1047448
A23: 2022-10 | D23: 201000 | E23: 115015 | F23: 96950 | G23: 154637 | H23: 4927 | I23: 220400 | J23: 107272 | L23: 69917 | M23: 472650 | N23: 1442768
A24: 2022-11 | D24: 204266 | E24: 200525 | F24: 54515 | G24: 107881 | H24: 4905 | I24: 68400 | J24: 44857 | L24: 61941 | M24: 389550 | N24: 1136840
A25: 2022-12 | D25: 220678 | E25: 114000 | F25: 48950 | G25: 118877 | H25: 5127 | I25: 37700 | J25: 27250 | L25: 74049 | M25: 389550 | N25: 1036181
A26: 2023-01 | D26: 218000 | E26: 306600 | F26: 48950 | G26: 90116 | I26: 95730 | J26: 84000 | L26: 68710 | M26: 389550 | N26: 1301656
A27: 2023-02 | D27: 220174 | E27: 115225 | F27: 583470 | G27: 95142 | H27: 4696 | I27: 100000 | J27: 41460 | L27: 62149 | M27: 444350 | N27: 1666666
A28: 2023-03 | D28: 218000 | E28: 108700 | F28: 48950 | G28: 90833 | H28: 8996 | I28: 79215 | J28: 84350 | K28: 47800 | L28: 67769 | M28: 437550 | N28: 1192163
A29: 2023-04 | D29: 218000 | E29: 128675 | F29: 52940 | G29: 87373 | H29: 4948 | I29: 127850 | J29: 22476 | L29: 66523 | M29: 389550 | N29: 1098335
A30: 2023-05 | D30: 218000 | E30: 222560 | F30: 48950 | G30: 93029 | H30: 4558 | I30: 68800 | J30: 23595 | L30: 60580 | M30: 391820 | N30: 1131892
A31: 2023-06 | D31: 221686 | E31: 106200 | F31: 132360 | G31: 90340 | H31: 4365 | I31: 70000 | J31: 5250 | L31: 72178 | M31: 414350 | N31: 1116729
A32: 2023-07 | D32: 218998 | E32: 120400 | F32: 48950 | G32: 93568 | H32: 4417 | I32: 105985 | J32: 90240 | L32: 63598 | M32: 406989 | N32: 1153145
A33: 2023-08 | D33: 218000 | E33: 104200 | F33: 48950 | G33: 121277 | H33: 4370 | I33: 67000 | J33: 86650 | K33: 25000 | L33: 67806 | M33: 533010 | N33: 1276263
A34: 2023-09 | D34: 220216 | E34: 136900 | F34: 56950 | G34: 105889 | H34: 4472 | I34: 76875 | J34: 14600 | L34: 61962 | M34: 389550 | N34: 1067414
A35: 2023-10 | D35: 218000 | E35: 100000 | F35: 98840 | G35: 127753 | H35: 4314 | I35: 70200 | J35: 43600 | L35: 64522 | M35: 433450 | N35: 1160679
A36: 2023-11 | D36: 222432 | E36: 138675 | F36: 48950 | G36: 97513 | H36: 4631 | I36: 37200 | J36: 114200 | L36: 67185 | M36: 397550 | N36: 1128336
A37: 2023-12 | D37: 228000 | E37: 124600 | F37: 48950 | G37: 92454 | H37: 4474 | I37: 133485 | J37: 239100 | L37: 155538 | M37: 443650 | N37: 1470251
A38: 2024-01 | D38: 230174 | E38: 104200 | F38: 122450 | G38: 100087 | H38: 4604 | I38: 62400 | J38: 73500 | L38: 69974 | M38: 413350 | N38: 1180739
A39: 2024-02 | D39: 228000 | E39: 134175 | F39: 72260 | G39: 115564 | I39: 91150 | J39: 55000 | L39: 62623 | M39: 393550 | N39: 1152322
A40: 2024-03 | D40: 229260 | E40: 109600 | F40: 203140 | G40: 107119 | H40: 8955 | I40: 43000 | J40: 95945 | K40: 51600 | L40: 69175 | M40: 393550 | N40: 1311344
A41: 2024-04 | D41: 231442 | E41: 156100 | F41: 137113 | G41: 100968 | H41: 4720 | I41: 172870 | J41: 39350 | L41: 66503 | M41: 393550 | N41: 1302616
A42: 2024-05 | D42: 228000 | E42: 110200 | F42: 69110 | G42: 111412 | H42: 4624 | I42: 40750 | J42: 39800 | L42: 79081 | M42: 413350 | N42: 1096327
A43: 2024-06 | D43: 229670 | E43: 396022 | F43: 102315 | G43: 128955 | H43: 4500 | I43: 71800 | J43: 71518 | L43: 61714 | M43: 397050 | N43: 1463544
A44: 2024-07 | D44: 230258 | E44: 100000 | F44: 56300 | G44: 126129 | H44: 4474 | I44: 78880 | J44: 127800 | L44: 73327 | M44: 528368 | N44: 1325536
A45: 2024-08 | D45: 229512 | E45: 103000 | F45: 166950 | G45: 144844 | H45: 4421 | I45: 93750 | J45: 63850 | K45: 25000 | L45: 64860 | M45: 469190 | N45: 1365377
A46: 2024-09 | D46: 228000 | E46: 121360 | F46: 66590 | G46: 145608 | H46: 4417 | I46: 40100 | J46: 410543 | L46: 62536 | M46: 427550 | N46: 1506704
A47: 2024-11 | B47: 119700 | C47: 315000 | D47: 229008 | E47: 103200 | F47: 56950 | G47: 227933 | H47: 4214 | I47: 70500 | L47: 71276 | N47: 1197781
A48: 2024-12 | B48: 119700 | C48: 315000 | D48: 247922 | E48: 100000 | F48: 476940 | G48: 111010 | H48: 4745 | I48: 43675 | J48: 33000 | L48: 12161 | M48: 35925 | N48: 1500078
A49: 2025-01 | B49: 119700 | C49: 315000 | D49: 248016 | E49: 114175 | F49: 137072 | I49: 84450 | L49: 123633 | N49: 1142046
A50: 2025-02 | G50: 106580 | H50: 4753 | N50: 111333
A51: 2025-03 | B51: 119700 | C51: 315000 | D51: 251122 | F51: 197664 | G51: 108145 | H51: 9534 | I51: 75500 | J51: 19000 | L51: 72751 | M51: 202377 | N51: 1370793
A52: 2025-04 | B52: 119700 | C52: 315000 | D52: 252253 | E52: 100000 | F52: 149834 | G52: 123550 | H52: 4784 | I52: 93500 | J52: 243870 | K52: 144000 | L52: 78067 | M52: 241500 | N52: 1866058
A53: 2025-05 | B53: 119700 | C53: 315000 | D53: 251450 | E53: 214390 | F53: 107285 | G53: 89242 | H53: 4529 | I53: 45400 | J53: 300800 | L53: 62140 | M53: 243275 | N53: 1753211
A54: 2025-06 | B54: 119700 | C54: 315000 | D54: 251724 | E54: 100000 | F54: 88297 | G54: 96399 | H54: 5419 | I54: 71150 | J54: 178540 | K54: 12000 | L54: 80064 | M54: 158232 | N54: 1476525
A55: 2025-07 | B55: 119700 | C55: 315000 | D55: 246000 | E55: 100000 | F55: 118558 | G55: 100318 | H55: 4915 | I55: 40750 | J55: 2192553 | L55: 241243 | M55: 250456 | N55: 3729493
A56: 2025-08 | B56: 119700 | C56: 315000 | D56: 249623 | E56: 182525 | F56: 101014 | G56: 141036 | H56: 4864 | I56: 342900 | J56: 1518573 | K56: 20030 | L56: 133875 | M56: 288661 | N56: 3417801
A57: 2025-09 | B57: 119700 | C57: 315000 | D57: 247008 | E57: 109500 | F57: 108150 | G57: 126605 | H57: 4481 | I57: 40100 | J57: 1127720 | K57: 20030 | L57: 137248 | M57: 335737 | N57: 2691279
A58: 2025-10 | B58: 132300 | C58: 319200 | D58: 248678 | E58: 276200 | F58: 94135 | G58: 168711 | H58: 4887 | I58: 71150 | J58: 828110 | K58: 20090 | L58: 295832 | M58: 23093 | N58: 2482386
A59: 2025-11 | B59: 132300 | C59: 319200 | D59: 249276 | E59: 131075 | F59: 121825 | G59: 111303 | H59: 4881 | I59: 38800 | J59: 958137 | L59: 165076 | M59: 25200 | N59: 2257073
A60: 2025-12 | B60: 132300 | C60: 319200 | D60: 249340 | E60: 131713 | F60: 44650 | G60: 108030 | H60: 4635 | I60: 71800 | J60: 837233 | L60: 207018 | M60: 235060 | N60: 2340979
A61: 2026-01 | B61: 132300 | C61: 319200 | D61: 263088 | E61: 100000 | F61: 142873 | G61: 85774 | H61: 5003 | I61: 70500 | J61: 688309 | L61: 123029 | M61: 150000 | N61: 2080076
A62: 2026-02 | B62: 149050 | C62: 355950 | D62: 258300 | E62: 106804 | F62: 20950 | G62: 91302 | I62: 307482 | J62: 589596 | K62: 45800 | L62: 234578 | N62: 2159812
A63: 2026-03 | B63: 149050 | C63: 355950 | D63: 260316 | E63: 144489 | F63: 45450 | G63: 84786 | H63: 4898 | I63: 54100 | J63: 405955 | L63: 171037 | N63: 1676031
A64: 2026-04 | B64: 149050 | C64: 355950 | D64: 258300 | E64: 137423 | F64: 19450 | G64: 95012 | H64: 9213 | I64: 75600 | J64: 1200659 | K64: 141698 | L64: 251171 | M64: 10000 | N64: 2703526
A65: 全期合計 | B65: 2173350 | C65: 5494650 | D65: 13852236 | E65: 8143141 | F65: 7954709 | G65: 6522042 | H65: 301678 | I65: 5242447 | J65: 14431215 | K65: 745560 | L65: 5564236 | M65: 20867630 | N65: 91292894

Sheet 收入明細
A1: 月份 | B1: 主類 | C1: 子類 | D1: 顯示名稱 | E1: 金額 | F1: 分類
A2: 2021-01 | B2: 元大定存利息 | D2: 元大定存利息 | E2: 416 | F2: 利息收入
A3: 2021-01 | B3: 元大定存利息 | D3: (未命名) | E3: 314 | F3: 其他收入
A4: 2021-01 | B4: 元大定存利息 | D4: (未命名) | E4: 416 | F4: 其他收入
A5: 2021-01 | B5: 元大定存利息 | D5: (未命名) | E5: 654 | F5: 其他收入
A6: 2021-01 | B6: 元大定存利息 | D6: (未命名) | E6: 1308 | F6: 其他收入
A7: 2021-01 | B7: 管理費收入 | D7: 管理費收入 | E7: 5919 | F7: 管理費收入
A8: 2021-01 | B8: 管理費收入 | D8: (未命名) | E8: 13746 | F8: 其他收入
A9: 2021-01 | B9: 管理費收入 | D9: (未命名) | E9: 2145711 | F9: 其他收入
A10: 2021-01 | B10: 裝潢保證金 | D10: 裝潢保證金 | E10: 0 | F10: 暫收款進
A11: 2021-01 | B11: 公設收入 | D11: 公設收入 | E11: 8810 | F11: 公設收入
A12: 2021-01 | B12: 管委會出席費回存 | D12: 管委會出席費回存 | E12: 2000 | F12: 出席費回存
A13: 2021-02 | B13: 元大活期利息 | D13: 元大活期利息 | E13: 0 | F13: 利息收入
A14: 2021-02 | B14: 元大定存利息 | C14: 683000006773 | D14: 元大定存利息 683000006773 | E14: 416 | F14: 利息收入
A15: 2021-02 | B15: 元大定存利息 | C15: 683000014551 | D15: 元大定存利息 683000014551 | E15: 314 | F15: 利息收入
A16: 2021-02 | B16: 元大定存利息 | C16: 683000006745 | D16: 元大定存利息 683000006745 | E16: 416 | F16: 利息收入
A17: 2021-02 | B17: 元大定存利息 | C17: 683000013365 | D17: 元大定存利息 683000013365 | E17: 654 | F17: 利息收入
A18: 2021-02 | B18: 元大定存利息 | C18: 683000016001 | D18: 元大定存利息 683000016001 | E18: 0 | F18: 利息收入
A19: 2021-02 | B19: 管理費收入 | C19: 109第三季 | D19: 管理費收入 109第三季 | E19: 4350 | F19: 管理費收入
A20: 2021-02 | B20: 管理費收入 | C20: 109第四季 | D20: 管理費收入 109第四季 | E20: 4350 | F20: 管理費收入
A21: 2021-02 | B21: 管理費收入 | C21: 110第一季 | D21: 管理費收入 110第一季 | E21: 862002 | F21: 管理費收入
A22: 2021-02 | B22: 管理費收入 | C22: 110第二季 | D22: 管理費收入 110第二季 | E22: 7812 | F22: 管理費收入
A23: 2021-02 | B23: 公設收入 | D23: 公設收入 | E23: 6320 | F23: 公設收入
A24: 2021-02 | B24: 管委會出席費回存 | D24: 管委會出席費回存 | E24: 3000 | F24: 出席費回存
A25: 2021-03 | B25: 元大活期利息 | D25: 元大活期利息 | E25: 0 | F25: 利息收入
A26: 2021-03 | B26: 元大定存利息 | C26: 683000006773 | D26: 元大定存利息 683000006773 | E26: 376 | F26: 利息收入
A27: 2021-03 | B27: 元大定存利息 | C27: 683000014551 | D27: 元大定存利息 683000014551 | E27: 284 | F27: 利息收入
A28: 2021-03 | B28: 元大定存利息 | C28: 683000006745 | D28: 元大定存利息 683000006745 | E28: 376 | F28: 利息收入
A29: 2021-03 | B29: 元大定存利息 | C29: 683000013365 | D29: 元大定存利息 683000013365 | E29: 591 | F29: 利息收入
A30: 2021-03 | B30: 元大定存利息 | C30: 683000016001 | D30: 元大定存利息 683000016001 | E30: 1308 | F30: 利息收入
A31: 2021-03 | B31: 元大定存利息 | C31: 683000016001 | D31: 元大定存利息 683000016001 | E31: 1181 | F31: 利息收入
A32: 2021-03 | B32: 管理費收入 | C32: 110年度Q1 | D32: 管理費收入 110年度Q1 | E32: 28632 | F32: 管理費收入
A33: 2021-03 | B33: 管理費收入 | C33: 110年度Q2 | D33: 管理費收入 110年度Q2 | E33: 40056 | F33: 管理費收入
A34: 2021-03 | B34: 公設收入 | D34: 公設收入 | E34: 11345 | F34: 公設收入
A35: 2021-03 | B35: 管委會出席費回存 | D35: 管委會出席費回存 | E35: 4000 | F35: 出席費回存
A36: 2021-03 | B36: 金創舊衣回收回饋金 | D36: 金創舊衣回收回饋金 | E36: 10000 | F36: 其他收入
A37: 2021-04 | B37: 元大活期利息 | D37: 元大活期利息 | E37: 0 | F37: 利息收入
A38: 2021-04 | B38: 元大定存利息 | C38: 683000006773 | D38: 元大定存利息 683000006773 | E38: 416 | F38: 利息收入
A39: 2021-04 | B39: 元大定存利息 | C39: 683000014551 | D39: 元大定存利息 683000014551 | E39: 314 | F39: 利息收入
A40: 2021-04 | B40: 元大定存利息 | C40: 683000006745 | D40: 元大定存利息 683000006745 | E40: 416 | F40: 利息收入
A41: 2021-04 | B41: 元大定存利息 | C41: 683000013365 | D41: 元大定存利息 683000013365 | E41: 654 | F41: 利息收入
A42: 2021-04 | B42: 元大定存利息 | C42: 683000016001 | D42: 元大定存利息 683000016001 | E42: 1308 | F42: 利息收入
A43: 2021-04 | B43: 管理費收入 | C43: 110年度Q1 | D43: 管理費收入 110年度Q1 | E43: 0 | F43: 管理費收入
A44: 2021-04 | B44: 管理費收入 | C44: 110年度Q2 | D44: 管理費收入 110年度Q2 | E44: 2301010 | F44: 管理費收入
A45: 2021-04 | B45: 公設收入 | D45: 公設收入 | E45: 8140 | F45: 公設收入
A46: 2021-04 | B46: 管委會出席費回存 | D46: 管委會出席費回存 | E46: 3000 | F46: 出席費回存
A47: 2021-05 | B47: 元大活期利息 | D47: 元大活期利息 | E47: 0 | F47: 利息收入
A48: 2021-05 | B48: 元大定存利息 | C48: 683000006773 | D48: 元大定存利息 683000006773 | E48: 403 | F48: 利息收入
A49: 2021-05 | B49: 元大定存利息 | C49: 683000014551 | D49: 元大定存利息 683000014551 | E49: 304 | F49: 利息收入
A50: 2021-05 | B50: 元大定存利息 | C50: 683000006745 | D50: 元大定存利息 683000006745 | E50: 403 | F50: 利息收入
A51: 2021-05 | B51: 元大定存利息 | C51: 683000013365 | D51: 元大定存利息 683000013365 | E51: 633 | F51: 利息收入
A52: 2021-05 | B52: 元大定存利息 | C52: 683000016001 | D52: 元大定存利息 683000016001 | E52: 1266 | F52: 利息收入
A53: 2021-05 | B53: 管理費收入 | C53: 110年度Q1 | D53: 管理費收入 110年度Q1 | E53: 6594 | F53: 管理費收入
A54: 2021-05 | B54: 管理費收入 | C54: 110年度Q2 | D54: 管理費收入 110年度Q2 | E54: 491571 | F54: 管理費收入
A55: 2021-05 | B55: 公設收入 | D55: 公設收入 | E55: 4375 | F55: 公設收入
A56: 2021-05 | B56: 管委會出席費回存 | D56: 管委會出席費回存 | E56: 2000 | F56: 出席費回存
A57: 2021-06 | B57: 元大活期利息 | D57: 元大活期利息 | E57: 4493 | F57: 利息收入
A58: 2021-06 | B58: 元大定存利息 | C58: 683000006773 | D58: 元大定存利息 683000006773 | E58: 416 | F58: 利息收入
A59: 2021-06 | B59: 元大定存利息 | C59: 683000014551 | D59: 元大定存利息 683000014551 | E59: 314 | F59: 利息收入
A60: 2021-06 | B60: 元大定存利息 | C60: 683000006745 | D60: 元大定存利息 683000006745 | E60: 416 | F60: 利息收入
A61: 2021-06 | B61: 元大定存利息 | C61: 683000013365 | D61: 元大定存利息 683000013365 | E61: 654 | F61: 利息收入
A62: 2021-06 | B62: 元大定存利息 | C62: 683000016001 | D62: 元大定存利息 683000016001 | E62: 1308 | F62: 利息收入
A63: 2021-06 | B63: 管理費收入 | C63: 110年度Q1(N5) | D63: 管理費收入 110年度Q1(N5) | E63: 8733 | F63: 管理費收入
A64: 2021-06 | B64: 管理費收入 | C64: 110年度Q2 | D64: 管理費收入 110年度Q2 | E64: 93930 | F64: 管理費收入
A65: 2021-06 | B65: 管理費收入 | C65: 110年度Q3(R22) | D65: 管理費收入 110年度Q3(R22) | E65: 8997 | F65: 管理費收入
A66: 2021-06 | B66: 公設收入 | D66: 公設收入 | E66: 750 | F66: 公設收入
A67: 2021-06 | B67: 管委會出席費回存 | D67: 管委會出席費回存 | E67: 1500 | F67: 出席費回存
A68: 2021-07 | B68: 元大活期利息 | D68: 元大活期利息 | E68: 0 | F68: 利息收入
A69: 2021-07 | B69: 元大定存利息 | C69: 683000006773 | D69: 元大定存利息 683000006773 | E69: 403 | F69: 利息收入
A70: 2021-07 | B70: 元大定存利息 | C70: 683000014551 | D70: 元大定存利息 683000014551 | E70: 304 | F70: 利息收入
A71: 2021-07 | B71: 元大定存利息 | C71: 683000006745 | D71: 元大定存利息 683000006745 | E71: 403 | F71: 利息收入
A72: 2021-07 | B72: 元大定存利息 | C72: 683000013365 | D72: 元大定存利息 683000013365 | E72: 633 | F72: 利息收入
A73: 2021-07 | B73: 元大定存利息 | C73: 683000016001 | D73: 元大定存利息 683000016001 | E73: 1266 | F73: 利息收入
A74: 2021-07 | B74: 管理費收入 | C74: 110年度Q1 (E07、F20、S16) | D74: 管理費收入 110年度Q1 (E07、F20、S16) | E74: 18363 | F74: 管理費收入
A75: 2021-07 | B75: 管理費收入 | C75: 110年度Q2 (B18、E07、E21、F13、F20、G09、I11、J18、K08、L06、M17、N05、O22、R10、S16) | D75: 管理費收入 110年度Q2 (B18、E07、E21、F13、F20、G09、I11、J18、K08、L06、M17、N05、O22、R10、S16) | E75: 106068 | F75: 管理費收入
A76: 2021-07 | B76: 管理費收入 | C76: 110年度Q3 | D76: 管理費收入 110年度Q3 | E76: 2448944 | F76: 管理費收入
A77: 2021-07 | B77: 管理費收入 | C77: 110年度Q4(G09) | D77: 管理費收入 110年度Q4(G09) | E77: 6450 | F77: 管理費收入
A78: 2021-07 | B78: 管理費收入 | C78: 111年度Q1(G09) | D78: 管理費收入 111年度Q1(G09) | E78: 6450 | F78: 管理費收入
A79: 2021-07 | B79: 公設收入 | D79: 公設收入 | E79: 500 | F79: 公設收入
A80: 2021-07 | B80: 管委會出席費回存 | D80: 管委會出席費回存 | E80: 500 | F80: 出席費回存
A81: 2021-07 | B81: 郁緁廠商賠償6萬元分別 7/6 $20000元，7/29 $40000元 | D81: 郁緁廠商賠償6萬元分別 7/6 $20000元，7/29 $40000元 | E81: 60000 | F81: 其他收入
A82: 2021-08 | B82: 元大活期利息 | D82: 元大活期利息 | E82: 0 | F82: 利息收入
A83: 2021-08 | B83: 元大定存利息 | C83: 683000006773 | D83: 元大定存利息 683000006773 | E83: 416 | F83: 利息收入
A84: 2021-08 | B84: 元大定存利息 | C84: 683000014551 | D84: 元大定存利息 683000014551 | E84: 314 | F84: 利息收入
A85: 2021-08 | B85: 元大定存利息 | C85: 683000006745 | D85: 元大定存利息 683000006745 | E85: 416 | F85: 利息收入
A86: 2021-08 | B86: 元大定存利息 | C86: 683000013365 | D86: 元大定存利息 683000013365 | E86: 654 | F86: 利息收入
A87: 2021-08 | B87: 元大定存利息 | C87: 683000016001 | D87: 元大定存利息 683000016001 | E87: 1308 | F87: 利息收入
A88: 2021-08 | B88: 管理費收入 | C88: 110年度Q2(G10、J21、J22、Q4、R11) | D88: 管理費收入 110年度Q2(G10、J21、J22、Q4、R11) | E88: 35868 | F88: 管理費收入
A89: 2021-08 | B89: 管理費收入 | C89: 110年度Q3 | D89: 管理費收入 110年度Q3 | E89: 466275 | F89: 管理費收入
A90: 2021-08 | B90: 公設收入 | D90: 公設收入 | E90: 960 | F90: 公設收入
A91: 2021-08 | B91: 管委會出席費回存 | D91: 管委會出席費回存 | E91: 1000 | F91: 出席費回存
A92: 2021-09 | B92: 元大活期利息 | D92: 元大活期利息 | E92: 0 | F92: 利息收入
A93: 2021-09 | B93: 元大定存利息 | C93: 683000006773 | D93: 元大定存利息 683000006773 | E93: 416 | F93: 利息收入
A94: 2021-09 | B94: 元大定存利息 | C94: 683000014551 | D94: 元大定存利息 683000014551 | E94: 314 | F94: 利息收入
A95: 2021-09 | B95: 元大定存利息 | C95: 683000006745 | D95: 元大定存利息 683000006745 | E95: 416 | F95: 利息收入
A96: 2021-09 | B96: 元大定存利息 | C96: 683000013365 | D96: 元大定存利息 683000013365 | E96: 654 | F96: 利息收入
A97: 2021-09 | B97: 元大定存利息 | C97: 683000016001 | D97: 元大定存利息 683000016001 | E97: 1308 | F97: 利息收入
A98: 2021-09 | B98: 管理費收入 | C98: 110年度Q2(C10) | D98: 管理費收入 110年度Q2(C10) | E98: 7827 | F98: 管理費收入
A99: 2021-09 | B99: 管理費收入 | C99: 110年度Q3 | D99: 管理費收入 110年度Q3 | E99: 65712 | F99: 管理費收入
A100: 2021-09 | B100: 公設收入 | D100: 公設收入 | E100: 3200 | F100: 公設收入
...

Sheet 支出明細
A1: 月份 | B1: 顯示名稱 | C1: 金額 | D1: 分類 | E1: Section | F1: 議案類別
A2: 小計：固定 661 項、非固定 1202 項、暫收款 0 項
A3: 小計：外牆修繕 14 項、納管 9 項、電梯 139 項、游泳池 39 項 — 給 PPT 第 4 頁 + 「議案-*」 sheet 用
A4: 2021-01 | B4: 零用金撥補(109/12) | C4: 4077 | D4: 零用金/出席費 | E4: 非固定
A5: 2021-01 | B5: 管會會出席費(110/01) | C5: 8000 | D5: 零用金/出席費 | E5: 非固定
A6: 2021-01 | B6: 電梯專用款撥補(110/01) | C6: 50000 | D6: 電梯專款撥款 | E6: 非固定 | F6: 電梯
A7: 2021-01 | B7: 德懋物業管理服務費(109/12) | C7: 359100 | D7: 管服費 | E7: 固定
A8: 2021-01 | B8: 順達清潔服務費(109/12) | C8: 99000 | D8: 清潔費 | E8: 固定
A9: 2021-01 | B9: 義明清潔服務費(109/12) | C9: 99000 | D9: 清潔費 | E9: 固定
A10: 2021-01 | B10: 侑昇-泳池機房保養(109/12) | C10: 3000 | D10: 泳池保養 | E10: 固定 | F10: 游泳池
A11: 2021-01 | B11: 崇友電梯(109/12)電梯保養 | C11: 100000 | D11: 電梯保養 | E11: 固定 | F11: 電梯
A12: 2021-01 | B12: AED(110/01)租賃費 | C12: 1500 | D12: AED | E12: 固定
A13: 2021-01 | B13: 御品寬頻(109/12)網路服務租賃 | C13: 9450 | D13: 電話/網路費 | E13: 固定
A14: 2021-01 | B14: 新鑫堯109/12清潔費(垃圾.資源回收) | C14: 24990 | D14: 清潔費 | E14: 固定
A15: 2021-01 | B15: 太古意門禁維護檢點費(109/12) | C15: 10000 | D15: 弱電/門禁 | E15: 固定
A16: 2021-01 | B16: 鑫禾機電保養費(109/12) | C16: 28000 | D16: 機電保養 | E16: 固定
A17: 2021-01 | B17: 景輝-園藝定期保養(12月) | C17: 28000 | D17: 園藝 | E17: 固定
A18: 2021-01 | B18: 鋐隆清潔用品 | C18: 1550 | D18: 其他 | E18: 非固定
A19: 2021-01 | B19: 英特康-磁扣100個 | C19: 4500 | D19: 其他 | E19: 非固定
A20: 2021-01 | B20: 崇友電梯維修-丙棟電梯紅外線光幕傳輸線 | C20: 1050 | D20: 電梯保養 | E20: 非固定 | F20: 電梯
A21: 2021-01 | B21: 10P乾粉滅火器性能檢查，數量323個 單價$120元，總計$120*323=$38,760元 | C21: 38760 | D21: 其他 | E21: 非固定
A22: 2021-01 | B22: 鑫禾 1.外圍人行道-噴灌重新配管(單價$1,000元) 2.丁棟景觀燈盤-漏電斷路器(單價$1,200元) 3.景觀池-1HP揚水馬達(單價$9,500元) 4.丙棟下水池-A泵主閘閥更換(單價$12,000元) 5.地下室、公廁-LED-MR16 (單價$395元*19盞=$7,505元) 5%稅金$1,560元，總計$1,000+1,200+9,500+12,000+7,505+1,560 =$32,765元 | C22: 32765 | D22: 其他 | E22: 非固定
A23: 2021-01 | B23: 禾順環保-高壓水刀清洗管路 單價$84,000元 | C23: 84000 | D23: 其他 | E23: 非固定
A24: 2021-01 | B24: 請求郁緁企業有限公司損害賠償民事訴訟第一審訴訟代理律師費(費用$45,000元，裁判費$1,000元，總計$46,000元) | C24: 46000 | D24: 其他 | E24: 非固定
A25: 2021-01 | B25: 水質檢測費-大腸桿菌群 | C25: 1200 | D25: 其他 | E25: 非固定
A26: 2021-01 | B26: 慶餘輸出-樓層貼紙 | C26: 8610 | D26: 其他 | E26: 非固定
A27: 2021-01 | B27: 中國石油-柴油 | C27: 9950 | D27: 其他 | E27: 非固定
A28: 2021-01 | B28: 退裝潢保證金 | C28: 80000 | D28: 退裝潢保證金 | E28: 非固定
A29: 2021-01 | B29: 社區電話費(109/12/01-109/12/31)(5630533) | C29: 880 | D29: 電話/網路費 | E29: 非固定
A30: 2021-01 | B30: 社區網路費(109/12/01-109/12/31)(Y123617) | C30: 2199 | D30: 電話/網路費 | E30: 非固定
A31: 2021-01 | B31: 社區網路費(109/12/01-109/12/31)(Y174790) | C31: 1899 | D31: 電話/網路費 | E31: 非固定
A32: 2021-01 | B32: 109年12月公共電費 | C32: 87413 | D32: 公共水電瓦斯 | E32: 非固定
... A38: 2021-02 | B38: 義明清潔服務費(110/02) | C38: 99000 | D38: 清潔費 | E38: 固定
A39: 2021-02 | B39: 侑昇-泳池機房保養(110/02) | C39: 3000 | D39: 泳池保養 | E39: 固定 | F39: 游泳池
A40: 2021-02 | B40: 崇友電梯(110/02)電梯保養 | C40: 100000 | D40: 電梯保養 | E40: 固定 | F40: 電梯
A41: 2021-02 | B41: AED(110/03)租賃費 | C41: 1500 | D41: AED | E41: 固定
A42: 2021-02 | B42: 御品寬頻(110/02)網路服務租賃 | C42: 9450 | D42: 電話/網路費 | E42: 固定
A43: 2021-02 | B43: 新鑫堯110/02清潔費(垃圾.資源回收) | C43: 24990 | D43: 清潔費 | E43: 固定
A44: 2021-02 | B44: 太古意門禁維護檢點費(110/02) | C44: 10000 | D44: 弱電/門禁 | E44: 非固定
A45: 2021-02 | B45: 鑫禾機電保養費(110/02) | C45: 28000 | D45: 機電保養 | E45: 固定
A46: 2021-02 | B46: 景輝-園藝定期保養(110年02月) | C46: 28000 | D46: 園藝 | E46: 固定
A47: 2021-02 | B47: 鋐隆清潔用品 小垃圾袋53*63一箱單價$950元 抽取式衛生紙一箱單價$950元 計$950+$950=$1900元 | C47: 1900 | D47: 清潔費 | E47: 非固定
A48: 2021-02 | B48: 禾順環保 水肥車協助更換管路 單價$8000元 | C48: 8000 | D48: 其他 | E48: 非固定
A49: 2021-02 | B49: 騰郡洗衣-清洗戶外抱枕 抱枕單價$80*39個=$3120元 工資單價$500元 計$3120+$500=$3620元 | C49: 3620 | D49: 其他 | E49: 非固定
A50: 2021-02 | B50: 景泰順 水質檢測費-大腸桿菌群 | C50: 1200 | D50: 其他 | E50: 非固定
A51: 2021-02 | B51: 義明清潔 110/02/02義明派清潔人員清洗B3車庫 | C51: 10000 | D51: 清潔費 | E51: 固定
A52: 2021-02 | B52: 鑫禾機電 109年度汙水申報 | C52: 22000 | D52: 機電保養 | E52: 非固定
... A64: 2021-03 | B64: 管委會出席費(110/04) | C64: 8000 | D64: 零用金/出席費 | E64: 非固定
A65: 2021-03 | B65: 電梯專用款撥補(110/03) | C65: 50000 | D65: 電梯專款撥款 | E65: 非固定 | F65: 電梯
A66: 2021-03 | B66: 德懋物業管理服務費(110/03) | C66: 359100 | D66: 管服費 | E66: 固定
A67: 2021-03 | B67: 順達清潔服務費(110/03) | C67: 99000 | D67: 清潔費 | E67: 固定
A68: 2021-03 | B68: 義明清潔服務費(110/03) | C68: 99000 | D68: 清潔費 | E68: 固定
A69: 2021-03 | B69: 侑昇-泳池機房保養(110/03) | C69: 3000 | D69: 泳池保養 | E69: 非固定 | F69: 游泳池
A70: 2021-03 | B70: 崇友電梯(110/03)電梯保養 | C70: 100000 | D70: 電梯保養 | E70: 固定 | F70: 電梯
A71: 2021-03 | B71: AED(110/04)租賃費 | C71: 1500 | D71: AED | E71: 固定
A72: 2021-03 | B72: 御品寬頻(110/03)網路服務租賃 | C72: 9450 | D72: 電話/網路費 | E72: 固定
A73: 2021-03 | B73: 新鑫堯110/03清潔費(垃圾.資源回收) | C73: 24990 | D73: 清潔費 | E73: 固定
A74: 2021-03 | B74: 太古意門禁維護檢點費(110/03) | C74: 10000 | D74: 弱電/門禁 | E74: 固定
A75: 2021-03 | B75: 鑫禾機電保養費(110/03) | C75: 28000 | D75: 機電保養 | E75: 固定
A76: 2021-03 | B76: 景輝-園藝定期保養(110/03) | C76: 28000 | D76: 園藝 | E76: 固定
A77: 2021-03 | B77: 景泰順 水質檢測費-大腸桿菌群 | C77: 1200 | D77: 其他 | E77: 非固定
A78: 2021-03 | B78: 松美裝潢 2/25瑜珈室、健身房捲簾保養維修 3/16撞球室、視聽室捲簾保養維修 | C78: 3000 | D78: 其他 | E78: 固定
A79: 2021-03 | B79: 崇友電梯-維修款 #2(甲棟貨梯) DD門控制器 PM門馬達組 PMD1{PG}轉接線 | C79: 24885 | D79: 電梯保養 | E79: 非固定 | F79: 電梯
A80: 2021-03 | B80: 崇友電梯-維修款 #6(丙棟貨梯) DD門控制器 PM門馬達組 PMD1{PG}轉接線 | C80: 24885 | D80: 電梯保養 | E80: 非固定 | F80: 電梯
A81: 2021-03 | B81: 全鋐企業社-鋁門窗維修 1.丁棟頂樓安全門，損壞維修(板金、焊接)$6000元 2.丁棟頂樓安全門，鎖更換$3500元 | C81: 9500 | D81: 其他 | E81: 非固定
A82: 2021-03 | B82: 鴻陽運動事業有限公司-氯錠 消毒藥劑:韓製氯錠3英寸90% 50KG/桶 $5250*6=$31500元 | C82: 31500 | D82: 其他 | E82: 非固定
A83: 2021-03 | B83: 儐順噴灌系統檢測費 | C83: 4500 | D83: 其他 | E83: 非固定
A84: 2021-03 | B84: 太古意 TA-390G車牌攝影機單價$10500元，5%稅金$525元 | C84: 11025 | D84: 弱電/門禁 | E84: 非固定
A85: 2021-03 | B85: 金伯亨 KS-9401(LED-10W球*1 3000K)單價$450元*7組=$3150元【桌球室崁燈】 改E27燈頭(LED-雪糕10W*1 L)單價$250元*10組=$2500元【車道】 拆裝工資$3000元 | C85: 8650 | D85: 其他 | E85: 非固定
A86: 2021-03 | B86: 鑫聲冷氣(媽媽教室) 禾聯落地箱型定頻專冷HO-1685/HIS-168 $84735元 禾聯壁掛1-1型定頻專冷HO-915/HI-91C $61530元 | C86: 146265 | D86: 其他 | E86: 非固定
A87: 2021-03 | B87: 110年3月20日區權會出席禮卷 總出席人數249人，一人200元，總計49800元 109年11月已購買21000元禮卷 需再添購$28800元禮卷 $49800-$21000=$28800元， 打99折，折扣後$28512元 | C87: 28512 | D87: 其他 | E87: 非固定
A88: 2021-03 | B88: 鑫禾機電 1.減壓閥墊片更新$800*3=$2400元 2.LED杯燈$395*6=$2370元 3.電燈感應器$650元 4.冷氣電源配置$22500元 5.透氣管改管$4200元 6.LED球泡燈$100*15=$1500元 7.5%稅金$1681元 | C88: 35301 | D88: 機電保養 | E88: 非固定
A89: 2021-03 | B89: 社區電話費(5630533)110.01.01~110.01.31 | C89: 1047 | D89: 電話/網路費 | E89: 非固定
A90: 2021-03 | B90: 社區網路費(Y123617)110.01.01~110.01.31 | C90: 2199 | D90: 電話/網路費 | E90: 非固定
A91: 2021-03 | B91: 社區網路費(Y174790)110.01.01~110.01.31 | C91: 1899 | D91: 電話/網路費 | E91: 非固定
A92: 2021-03 | B92: 社區電話費(5630533)110.02.01~110.02.28 | C92: 1157 | D92: 電話/網路費 | E92: 非固定
... A102: 2021-04 | B102: 義明清潔服務費(110/04) 總計$99,000元 | C102: 99000 | D102: 清潔服務費 | E102: 固定
A103: 2021-04 | B103: 侑昇-泳池機房保養(110/04) 總計$3,000元 | C103: 3000 | D103: 其他支出 | E103: 固定 | F103: 游泳池
A104: 2021-04 | B104: 崇友電梯(110/04)電梯保養 總計$100,000元 | C104: 100000 | D104: 電梯保養與修繕 | E104: 固定
A105: 2021-04 | B105: AED(110/05)租賃費 總計$1,500元 | C105: 1500 | D105: 機電/消防/弱電/AED | E105: 固定
A106: 2021-04 | B106: 御品寬頻(110/04)網路服務租賃 總計$9,450元 | C106: 9450 | D106: 機電/消防/弱電/AED | E106: 固定
A107: 2021-04 | B107: 新鑫堯110/04 廢棄物清除$25,000元 清潔費$5,000元 總計$30,000元 | C107: 30000 | D107: 垃圾廢棄物/園藝 | E107: 固定
A108: 2021-04 | B108: 太古意門禁維護檢點費(110/04) 總計$10,000元 | C108: 10000 | D108: 機電/消防/弱電/AED | E108: 固定
A109: 2021-04 | B109: 鑫禾機電保養費(110/04) 總計$28,000元 | C109: 28000 | D109: 機電/消防/弱電/AED | E109: 固定
A110: 2021-04 | B110: 景輝-園藝定期保養(110/04) 總計$28,000元 | C110: 28000 | D110: 垃圾廢棄物/園藝 | E110: 固定
A111: 2021-04 | B111: 景泰順 水質檢測費-大腸桿菌群 總計$1,200元 | C111: 1200 | D111: 其他支出 | E111: 非固定
A112: 2021-04 | B112: 鋐隆清潔用品 擦手紙1箱$420元 小捲衛生紙1箱$400元 紅龍珍珠洗手乳2瓶$360元 小捲衛生紙1箱$400元 大白垃圾袋25kg $1150元 總計$2730元 | C112: 2730 | D112: 清潔服務費 | E112: 非固定
A113: 2021-04 | B113: 鑫禾機電 1.管路配管1式$800元(S13前花圃) 2.無熔絲電源開關2只$1000*2=$2000元(腳踏車室冷氣迴路) 3.電燈感應器1只$650元(B1-699車位) 4.T5層板燈具1盞$300元(B1-1號機車位) 5.MR16杯燈3組$395*3=1185元(戊棟1樓信箱區，丁棟6樓) 6.5%稅金$247元 總計$5,182元 | C113: 5182 | D113: 機電/消防/弱電/AED | E113: 非固定
A114: 2021-04 | B114: 禾順環保 1.疏通排水總管1式$3000元 2.拆裝馬桶及檢查馬桶底部滲水1個$3000元 3.拆裝馬桶及疏通排糞總管1式$8000元 (疏通長度50米)糞管 總計$14,000元 | C114: 14000 | D114: 其他支出 | E114: 非固定
A115: 2021-04 | B115: 育丞石材 石材更換 1.流水景觀瀑布外水池、人行步道石材破損、7-11門市前人行道上地板破裂$15000元 2.丙棟1樓M樓把手受損更換$3000元 鬆動處理 1.人行道花園石材單價$300*40=$12000元 2.1樓公設，小木屋散步區單價$300*8=$2400元 3.內步道景觀池旁單價$300*9=$2700元 4.室內電梯間接地坪單價$300*2=$600元 總計$35,700元 | C115: 35700 | D115: 垃圾廢棄物/園藝 | E115: 非固定 | F115: 電梯
A116: 2021-04 | B116: 社區電話費(5630533)110.03.01~110.03.31 | C116: 1123 | D116: 電話/網路費 | E116: 非固定
A117: 2021-04 | B117: 社區網路費(Y123617)110.03.01~110.03.31 | C117: 2199 | D117: 電話/網路費 | E117: 非固定
A118: 2021-04 | B118: 社區網路費(Y174790)110.03.01~110.03.31 | C118: 1899 | D118: 電話/網路費 | E118: 非固定
A119: 2021-04 | B119: 公共電費(110.02.17至110.03.15) | C119: 85178 | D119: 公共水電瓦斯 | E119: 非固定
A120: 2021-04 | B120: 自來水費(110.01.07至110.03.08) | C120: 4513 | D120: 公共水電瓦斯 | E120: 非固定
A121: 2021-05 | B121: 零用金撥補(110/05) 總計$13,296元 | C121: 13296 | D121: 內部轉帳 | E121: 非固定
A122: 2021-05 | B122: 管委會出席費用(預領) 總計$8000元 | C122: 8000 | D122: 內部轉帳 | E122: 非固定
A123: 2021-05 | B123: 電梯專用款撥補(110/05) 總計$50000元 | C123: 50000 | D123: 內部轉帳 | E123: 非固定
A124: 2021-05 | B124: 德懋物業公司(110/05)管理服務費：社區經理乙員，社區秘書乙員，警衛服務人員兩哨。 總計$359,100元 | C124: 359100 | D124: 其他支出 | E124: 固定
A125: 2021-05 | B125: 順達清潔服務費(110/05) 總計$99,000元 | C125: 99000 | D125: 清潔服務費 | E125: 固定
...

Sheet 收入分類矩陣
A1: 月份 | B1: 管理費收入 | C1: 利息收入 | D1: 公設收入 | E1: 出席費回存 | F1: 贊助/活動 | G1: 暫收款進 | H1: 內部轉帳 | I1: 其他收入 | J1: 合計
A2: 2021-01 | B2: 5919 | C2: 416 | D2: 8810 | E2: 2000 | I2: 2162149 | J2: 2179294
A3: 2021-02 | B3: 878514 | C3: 1800 | D3: 6320 | E3: 3000 | J3: 889634
A4: 2021-03 | B4: 68688 | C4: 4116 | D4: 11345 | E4: 4000 | I4: 10000 | J4: 98149
A5: 2021-04 | B5: 2301010 | C5: 3108 | D5: 8140 | E5: 3000 | J5: 2315258
A6: 2021-05 | B6: 498165 | C6: 3009 | D6: 4375 | E6: 2000 | J6: 507549
A7: 2021-06 | B7: 111660 | C7: 7601 | D7: 750 | E7: 1500 | J7: 121511
A8: 2021-07 | B8: 2586275 | C8: 3009 | D8: 500 | E8: 500 | I8: 60000 | J8: 2650284
A9: 2021-08 | B9: 502143 | C9: 3108 | D9: 960 | E9: 1000 | J9: 507211
A10: 2021-09 | B10: 73539 | C10: 3108 | D10: 3200 | E10: 1000 | J10: 80847
A11: 2021-10 | B11: 2362716 | C11: 3009 | D11: 5320 | E11: 2500 | J11: 2373545
A12: 2021-11 | B12: 584076 | C12: 3108 | D12: 7710 | E12: 2500 | I12: 21210 | J12: 618604
A13: 2021-12 | B13: 184344 | C13: 5862 | D13: 8435 | E13: 500 | J13: 199141
A14: 2022-01 | B14: 2394522 | C14: 3108 | D14: 5605 | E14: 1000 | I14: 970 | J14: 2405205
A15: 2022-02 | B15: 655662 | C15: 1800 | J15: 657462
A16: 2022-03 | B16: 76940 | C16: 4116 | D16: 15305 | E16: 3000 | I16: 1116507 | J16: 1215868
A17: 2022-04 | B17: 2955381 | C17: 2794 | D17: 6160 | E17: 4000 | J17: 2968335
A18: 2022-05 | B18: 703893 | C18: 3132 | D18: 5895 | E18: 1500 | J18: 714420
A19: 2022-06 | B19: 85452 | C19: 5205 | D19: 9560 | E19: 2000 | J19: 102217
A20: 2022-07 | B20: 2947852 | C20: 3860 | D20: 5295 | E20: 1500 | I20: 6177 | J20: 2964684
A21: 2022-08 | B21: 835890 | C21: 4545 | D21: 5035 | E21: 2500 | J21: 847970
A22: 2022-09 | B22: 132612 | C22: 4306 | D22: 9090 | E22: 3000 | J22: 149008
A23: 2022-10 | B23: 3223413 | C23: 5431 | D23: 6625 | E23: 2000 | J23: 3237469
A24: 2022-11 | B24: 484833 | C24: 6189 | D24: 7565 | E24: 2500 | J24: 501087
A25: 2022-12 | B25: 68334 | C25: 5704 | D25: 7450 | E25: 3000 | J25: 84488
A26: 2023-01 | B26: 3226644 | C26: 5986 | D26: 5050 | E26: 4000 | F26: 3000 | J26: 3244680
A27: 2023-02 | B27: 524196 | C27: 4888 | D27: 4570 | E27: 3000 | F27: 4000 | J27: 540654
A28: 2023-03 | B28: 138576 | C28: 7214 | D28: 11630 | E28: 3000 | I28: 16720 | J28: 177140
A29: 2023-04 | B29: 2931309 | C29: 6453 | D29: 6025 | E29: 4000 | J29: 2947787
A30: 2023-05 | B30: 855633 | C30: 8250 | D30: 8020 | E30: 1000 | J30: 872903
A31: 2023-06 | B31: 118779 | C31: 8148 | D31: 7290 | E31: 500 | I31: 2400 | J31: 137117
A32: 2023-07 | B32: 3146871 | C32: 7712 | D32: 6815 | E32: 1000 | I32: 28710 | J32: 3191108
A33: 2023-08 | B33: 480417 | C33: 8892 | D33: 4660 | E33: 1000 | I33: 18420 | J33: 513389
A34: 2023-09 | B34: 75744 | C34: 8388 | D34: 20820 | E34: 1000 | I34: 120 | J34: 106072
A35: 2023-10 | B35: 3466637 | C35: 8514 | D35: 8800 | E35: 2500 | J35: 3486451
A36: 2023-11 | B36: 476505 | C36: 9790 | D36: 10400 | E36: 1500 | J36: 498195
A37: 2023-12 | B37: 15528 | C37: 9124 | D37: 11830 | E37: 3500 | F37: 308 | I37: 21900 | J37: 62190
A38: 2024-01 | B38: 3609691 | C38: 9088 | D38: 13310 | E38: 1500 | J38: 3633589
A39: 2024-02 | B39: 284220 | C39: 10032 | D39: 6180 | E39: 1000 | J39: 301432
A40: 2024-03 | B40: 28980 | C40: 8868 | J40: 37848
A41: 2024-04 | B41: 3071838 | C41: 9681 | D41: 19800 | E41: 4000 | I41: 16720 | J41: 3122039
A42: 2024-05 | B42: 673380 | C42: 10341 | D42: 11360 | E42: 1500 | J42: 696581
A43: 2024-06 | B43: 100986 | C43: 10449 | D43: 10750 | E43: 1500 | J43: 123685
A44: 2024-07 | B44: 3374370 | C44: 9632 | D44: 8080 | E44: 3000 | I44: 21780 | J44: 3416862
A45: 2024-08 | B45: 442743 | C45: 11030 | D45: 10340 | E45: 2500 | I45: 26430 | J45: 493043
A46: 2024-09 | B46: 53937 | C46: 10290 | D46: 12450 | E46: 3500 | I46: 4020 | J46: 84197
A47: 2024-11 | B47: 305373 | C47: 11217 | D47: 19460 | E47: 5000 | J47: 341050
A48: 2024-12 | B48: 111621 | C48: 10640 | D48: 11380 | E48: 3500 | J48: 137141
A49: 2025-01 | B49: 1824402 | C49: 7342 | D49: 7980 | E49: 3500 | J49: 1843224
A50: 2025-02 | B50: 1639314 | C50: 10456 | J50: 1649770
A51: 2025-03 | B51: 128328 | C51: 12348 | D51: 9410 | E51: 4000 | J51: 154086
A52: 2025-04 | B52: 2459034 | C52: 10027 | D52: 9520 | E52: 2500 | J52: 2481081
A53: 2025-05 | B53: 1448643 | C53: 9946 | D53: 21650 | E53: 3000 | J53: 1483239
A54: 2025-06 | B54: 110625 | C54: 10319 | D54: 6050 | E54: 2000 | J54: 128994
A55: 2025-07 | B55: 2087811 | C55: 8836 | D55: 17210 | E55: 1000 | I55: 5026574 | J55: 7141431
A56: 2025-08 | B56: 1558284 | C56: 9057 | D56: 10150 | E56: 3500 | G56: 20000 | I56: 89600 | J56: 1690591
A57: 2025-09 | B57: 88322 | C57: 8755 | D57: 12760 | E57: 1000 | G57: 80000 | I57: 142017 | J57: 332854
A58: 2025-10 | B58: 2462318 | C58: 7526 | D58: 8100 | E58: 2500 | J58: 2480444
A59: 2025-11 | B59: 1457330 | C59: 7338 | D59: 10720 | E59: 2500 | G59: 60000 | I59: 161370 | J59: 1699258
A60: 2025-12 | B60: 1257126 | C60: 14940 | D60: 13220 | E60: 3000 | G60: 20000 | I60: 237215 | J60: 1545501
A61: 2026-01 | B61: 2877166 | C61: 6488 | D61: 11340 | E61: 1500 | G61: 20000 | J61: 2916494
A62: 2026-02 | B62: 1234742 | C62: 6989 | D62: 6520 | H62: 50000 | J62: 1298251
A63: 2026-03 | B63: 1316371 | C63: 7199 | D63: 11560 | E63: 3000 | F63: 15095 | H63: 36 | J63: 1353261
A64: 2026-04 | B64: 3114907 | C64: 6301 | D64: 8480 | E64: 60500 | G64: 20000 | H64: 2289346 | J64: 5499534
A65: 全期合計 | B65: 77300534 | C65: 439938 | D65: 543140 | E65: 196000 | F65: 22403 | G65: 220000 | H65: 2339382 | I65: 9191009 | J65: 90252406

Sheet 議案-外牆修繕
A1: 議案彙整 — 外牆修繕
A2: 外牆磁磚修繕系列 (天幕高空 + 蜘蛛人施工 + 坦茂磁磚採購 + 建築師公會鑑定報告)
A4: ─── 統計（公式自動計算）───
A5: 合計金額 (NT$) | B5: =SUMIFS(支出明細!C:C,支出明細!F:F,"外牆修繕") | D5: ← SUMIFS 公式：sum of C where F='外牆修繕'
A6: 筆數 | B6: =COUNTIF(支出明細!F:F,"外牆修繕") | D6: ← COUNTIF 公式：count of F='外牆修繕'
A7: 期間 | B7: 2025-07 ~ 2026-04 | D7: ← Python pre-compute (min/max month)
A9: ─── 明細（每 cell = 「支出明細」 sheet 對應 row 的公式 reference）───
A10: 月份 | B10: 金額 (NT$) | C10: 工程項目 | D10: 分類 | E10: Section | F10: (支出明細 row #)
A11: =支出明細!A1549 | B11: =支出明細!C1549 | C11: =支出明細!B1549 | D11: =支出明細!D1549 | E11: =支出明細!E1549 | F11: 1549
A12: =支出明細!A1617 | B12: =支出明細!C1617 | C12: =支出明細!B1617 | D12: =支出明細!D1617 | E12: =支出明細!E1617 | F12: 1618
A13: =支出明細!A1578 | B13: =支出明細!C1578 | C13: =支出明細!B1578 | D13: =支出明細!D1578 | E13: =支出明細!E1578 | F13: 1579
A14: =支出明細!A1661 | B14: =支出明細!C1661 | C14: =支出明細!B1661 | D14: =支出明細!D1661 | E14: =支出明細!E1661 | F14: 1662
A15: =支出明細!A1512 | B15: =支出明細!C1512 | C15: =支出明細!B1512 | D15: =支出明細!D1512 | E15: =支出明細!E1512 | F15: 1512
A16: =支出明細!A1858 | B16: =支出明細!C1858 | C16: =支出明細!B1858 | D16: =支出明細!D1858 | E16: =支出明細!E1858 | F16: 1859
A17: =支出明細!A1706 | B17: =支出明細!C1706 | C17: =支出明細!B1706 | D17: =支出明細!D1706 | E17: =支出明細!E1706 | F17: 1707
A18: =支出明細!A1774 | B18: =支出明細!C1774 | C18: =支出明細!B1774 | D18: =支出明細!D1774 | E18: =支出明細!E1774 | F18: 1775
A19: =支出明細!A1702 | B19: =支出明細!C1702 | C19: =支出明細!B1702 | D19: =支出明細!D1702 | E19: =支出明細!E1702 | F19: 1703
A20: =支出明細!A1703 | B20: =支出明細!C1703 | C20: =支出明細!B1703 | D20: =支出明細!D1703 | E20: =支出明細!E1703 | F20: 1704
A21: =支出明細!A1852 | B21: =支出明細!C1852 | C21: =支出明細!B1852 | D21: =支出明細!D1852 | E21: =支出明細!E1852 | F21: 1853
A22: =支出明細!A1631 | B22: =支出明細!C1631 | C22: =支出明細!B1631 | D22: =支出明細!D1631 | E22: =支出明細!E1631 | F22: 1632
A23: =支出明細!A1550 | B23: =支出明細!C1550 | C23: =支出明細!B1550 | D23: =支出明細!D1550 | E23: =支出明細!E1550 | F23: 1550
A24: =支出明細!A1816 | B24: =支出明細!C1816 | C24: =支出明細!B1816 | D24: =支出明細!D1816 | E24: =支出明細!E1816 | F24: 1817
A25: 明細加總（應 = 上方統計 B5） | B25: =SUM(B11:B24)
A26: 差額 (B5 − 明細加總) | B26: =B5-B25 | D26: ← 應為 0；若 ≠ 0 表示 SUMIFS 抓的 row ≠ 明細列出的 row

Sheet 議案-納管
A1: 議案彙整 — 納管
A2: 汙水管路納管工程 (慈濟路人行道納管 + B3 汙水自動控制系統 + 配管 / 抽水 / 雜項)
A4: ─── 統計（公式自動計算）───
A5: 合計金額 (NT$) | B5: =SUMIFS(支出明細!C:C,支出明細!F:F,"納管") | D5: ← SUMIFS 公式：sum of C where F='納管'
A6: 筆數 | B6: =COUNTIF(支出明細!F:F,"納管") | D6: ← COUNTIF 公式：count of F='納管'
A7: 期間 | B7: 2025-04 ~ 2026-06 | D7: ← Python pre-compute (min/max month)
A9: ─── 明細（每 cell = 「支出明細」 sheet 對應 row 的公式 reference）───
A10: 月份 | B10: 金額 (NT$) | C10: 工程項目 | D10: 分類 | E10: Section | F10: (支出明細 row #)
A11: =支出明細!A1503 | B11: =支出明細!C1503 | C11: =支出明細!B1503 | D11: =支出明細!D1503 | E11: =支出明細!E1503 | F11: 1503
A12: =支出明細!A1516 | B12: =支出明細!C1516 | C12: =支出明細!B1516 | D12: =支出明細!D1516 | E12: =支出明細!E1516 | F12: 1516
A13: =支出明細!A1864 | B13: =支出明細!C1864 | C13: =支出明細!B1864 | D13: =支出明細!D1864 | E13: =支出明細!E1864 | F13: 1865
A14: =支出明細!A1856 | B14: =支出明細!C1856 | C14: =支出明細!B1856 | D14: =支出明細!D1856 | E14: =支出明細!E1856 | F14: 1857
A15: =支出明細!A1446 | B15: =支出明細!C1446 | C15: =支出明細!B1446 | D15: =支出明細!D1446 | E15: =支出明細!E1446 | F15: 1446
A16: =支出明細!A1746 | B16: =支出明細!C1746 | C16: =支出明細!B1746 | D16: =支出明細!D1746 | E16: =支出明細!E1746 | F16: 1747
A17: =支出明細!A1416 | B17: =支出明細!C1416 | C17: =支出明細!B1416 | D17: =支出明細!D1416 | E17: =支出明細!E1416 | F17: 1416
A18: =支出明細!A1779 | B18: =支出明細!C1779 | C18: =支出明細!B1779 | D18: =支出明細!D1779 | E18: =支出明細!E1779 | F18: 1780
A19: =支出明細!A1413 | B19: =支出明細!C1413 | C19: =支出明細!B1413 | D19: =支出明細!D1413 | E19: =支出明細!E1413 | F19: 1413
A20: 明細加總（應 = 上方統計 B5） | B20: =SUM(B11:B19)
A21: 差額 (B5 − 明細加總) | B21: =B5-B20 | D21: ← 應為 0；若 ≠ 0 表示 SUMIFS 抓的 row ≠ 明細列出的 row

Sheet 議案-電梯
A1: 議案彙整 — 電梯
A2: 電梯議案 (崇友月保養費 + 變頻器/控制板/HCD顯示器/微壓按鈕 等零件修繕) — 排除電梯專用款撥補
A4: ─── 統計（公式自動計算）───
A5: 合計金額 (NT$) | B5: =SUMIFS(支出明細!C:C,支出明細!F:F,"電梯") | D5: ← SUMIFS 公式：sum of C where F='電梯'
A6: 筆數 | B6: =COUNTIF(支出明細!F:F,"電梯") | D6: ← COUNTIF 公式：count of F='電梯'
A7: 期間 | B7: 2021-01 ~ 2026-04 | D7: ← Python pre-compute (min/max month)
A9: ─── 明細（每 cell = 「支出明細」 sheet 對應 row 的公式 reference）───
A10: 月份 | B10: 金額 (NT$) | C10: 工程項目 | D10: 分類 | E10: Section | F10: (支出明細 row #)
A11: =支出明細!A687 | B11: =支出明細!C687 | C11: =支出明細!B687 | D11: =支出明細!D687 | E11: =支出明細!E687 | F11: 687
A12: =支出明細!A1176 | B12: =支出明細!C1176 | C12: =支出明細!B1176 | D12: =支出明細!D1176 | E12: =支出明細!E1176 | F12: 1176
A13: =支出明細!A641 | B13: =支出明細!C641 | C13: =支出明細!B641 | D13: =支出明細!D641 | E13: =支出明細!E641 | F13: 641
A14: =支出明細!A800 | B14: =支出明細!C800 | C14: =支出明細!B800 | D14: =支出明細!D800 | E14: =支出明細!E800 | F14: 800
A15: =支出明細!A1434 | B15: =支出明細!C1434 | C15: =支出明細!B1434 | D15: =支出明細!D1434 | E15: =支出明細!E1434 | F15: 1434
A16: =支出明細!A1608 | B16: =支出明細!C1608 | C16: =支出明細!B1608 | D16: =支出明細!D1608 | E16: =支出明細!E1608 | F16: 1609
A17: =支出明細!A168 | B17: =支出明細!C168 | C17: =支出明細!B168 | D17: =支出明細!D168 | E17: =支出明細!E168 | F17: 168
A18: =支出明細!A1443 | B18: =支出明細!C1443 | C18: =支出明細!B1443 | D18: =支出明細!D1443 | E18: =支出明細!E1443 | F18: 1443
A19: =支出明細!A1175 | B19: =支出明細!C1175 | C19: =支出明細!B1175 | D19: =支出明細!D1175 | E19: =支出明細!E1175 | F19: 1175
A20: =支出明細!A1472 | B20: =支出明細!C1472 | C20: =支出明細!B1472 | D20: =支出明細!D1472 | E20: =支出明細!E1472 | F20: 1472
A21: =支出明細!A1541 | B21: =支出明細!C1541 | C21: =支出明細!B1541 | D21: =支出明細!D1541 | E21: =支出明細!E1541 | F21: 1541
A22: =支出明細!A1179 | B22: =支出明細!C1179 | C22: =支出明細!B1179 | D22: =支出明細!D1179 | E22: =支出明細!E1179 | F22: 1179
A23: =支出明細!A1539 | B23: =支出明細!C1539 | C23: =支出明細!B1539 | D23: =支出明細!D1539 | E23: =支出明細!E1539 | F23: 1539
A24: =支出明細!A1408 | B24: =支出明細!C1408 | C24: =支出明細!B1408 | D24: =支出明細!D1408 | E24: =支出明細!E1408 | F24: 1408
A25: =支出明細!A1614 | B25: =支出明細!C1614 | C25: =支出明細!B1614 | D25: =支出明細!D1614 | E25: =支出明細!E1614 | F25: 1615
A26: =支出明細!A1471 | B26: =支出明細!C1471 | C26: =支出明細!B1471 | D26: =支出明細!D1471 | E26: =支出明細!E1471 | F26: 1471
A27: =支出明細!A473 | B27: =支出明細!C473 | C27: =支出明細!B473 | D27: =支出明細!D473 | E27: =支出明細!E473 | F27: 473
A28: =支出明細!A1114 | B28: =支出明細!C1114 | C28: =支出明細!B1114 | D28: =支出明細!D1114 | E28: =支出明細!E1114 | F28: 1114
A29: =支出明細!A131 | B29: =支出明細!C131 | C29: =支出明細!B131 | D29: =支出明細!D131 | E29: =支出明細!E131 | F29: 131
A30: =支出明細!A108 | B30: =支出明細!C108 | C30: =支出明細!B108 | D30: =支出明細!D108 | E30: =支出明細!E108 | F30: 108
A31: =支出明細!A1694 | B31: =支出明細!C1694 | C31: =支出明細!B1694 | D31: =支出明細!D1694 | E31: =支出明細!E1694 | F31: 1695
A32: =支出明細!A1806 | B32: =支出明細!C1806 | C32: =支出明細!B1806 | D32: =支出明細!D1806 | E32: =支出明細!E1806 | F32: 1807
A33: =支出明細!A72 | B33: =支出明細!C72 | C33: =支出明細!B72 | D33: =支出明細!D72 | E33: =支出明細!E72 | F33: 72
A34: =支出明細!A73 | B34: =支出明細!C73 | C34: =支出明細!B73 | D34: =支出明細!D73 | E34: =支出明細!E73 | F34: 73
A35: =支出明細!A965 | B35: =支出明細!C965 | C35: =支出明細!B965 | D35: =支出明細!D965 | E35: =支出明細!E965 | F35: 965
A36: =支出明細!A447 | B36: =支出明細!C447 | C36: =支出明細!B447 | D36: =支出明細!D447 | E36: =支出明細!E447 | F36: 447
A37: =支出明細!A799 | B37: =支出明細!C799 | C37: =支出明細!B799 | D37: =支出明細!D799 | E37: =支出明細!E799 | F37: 799
A38: =支出明細!A388 | B38: =支出明細!C388 | C38: =支出明細!B388 | D38: =支出明細!D388 | E38: =支出明細!E388 | F38: 388
A39: =支出明細!A332 | B39: =支出明細!C332 | C39: =支出明細!B332 | D39: =支出明細!D332 | E39: =支出明細!E332 | F39: 332
A40: =支出明細!A1178 | B40: =支出明細!C1178 | C40: =支出明細!B1178 | D40: =支出明細!D1178 | E40: =支出明細!E1178 | F40: 1178
A41: =支出明細!A1409 | B41: =支出明細!C1409 | C41: =支出明細!B1409 | D41: =支出明細!D1409 | E41: =支出明細!E1409 | F41: 1409
A42: =支出明細!A1671 | B42: =支出明細!C1671 | C42: =支出明細!B1671 | D42: =支出明細!D1671 | E42: =支出明細!E1671 | F42: 1672
A43: =支出明細!A191 | B43: =支出明細!C191 | C43: =支出明細!B191 | D43: =支出明細!D191 | E43: =支出明細!E191 | F43: 191
A44: =支出明細!A582 | B44: =支出明細!C582 | C44: =支出明細!B582 | D44: =支出明細!D582 | E44: =支出明細!E582 | F44: 582
A45: =支出明細!A715 | B45: =支出明細!C715 | C45: =支出明細!B715 | D45: =支出明細!D715 | E45: =支出明細!E715 | F45: 715
A46: =支出明細!A909 | B46: =支出明細!C909 | C46: =支出明細!B909 | D46: =支出明細!D909 | E46: =支出明細!E909 | F46: 909
A47: =支出明細!A611 | B47: =支出明細!C611 | C47: =支出明細!B611 | D47: =支出明細!D611 | E47: =支出明細!E611 | F47: 611
A48: =支出明細!A774 | B48: =支出明細!C774 | C48: =支出明細!B774 | D48: =支出明細!D774 | E48: =支出明細!E774 | F48: 774
A49: =支出明細!A966 | B49: =支出明細!C966 | C49: =支出明細!B966 | D49: =支出明細!D966 | E49: =支出明細!E966 | F49: 966
A50: =支出明細!A1055 | B50: =支出明細!C1055 | C50: =支出明細!B1055 | D50: =支出明細!D1055 | E50: =支出明細!E1055 | F50: 1055
A51: =支出明細!A1350 | B51: =支出明細!C1350 | C51: =支出明細!B1350 | D51: =支出明細!D1350 | E51: =支出明細!E1350 | F51: 1350
A52: =支出明細!A1657 | B52: =支出明細!C1657 | C52: =支出明細!B1657 | D52: =支出明細!D1657 | E52: =支出明細!E1657 | F52: 1658
A53: =支出明細!A1845 | B53: =支出明細!C1845 | C53: =支出明細!B1845 | D53: =支出明細!D1845 | E53: =支出明細!E1845 | F53: 1846
A54: =支出明細!A448 | B54: =支出明細!C448 | C54: =支出明細!B448 | D54: =支出明細!D448 | E54: =支出明細!E448 | F54: 448
A55: =支出明細!A772 | B55: =支出明細!C772 | C55: =支出明細!B772 | D55: =支出明細!D772 | E55: =支出明細!E772 | F55: 772
A56: =支出明細!A995 | B56: =支出明細!C995 | C56: =支出明細!B995 | D56: =支出明細!D995 | E56: =支出明細!E995 | F56: 995
A57: =支出明細!A302 | B57: =支出明細!C302 | C57: =支出明細!B302 | D57: =支出明細!D302 | E57: =支出明細!E302 | F57: 302
A58: =支出明細!A389 | B58: =支出明細!C389 | C58: =支出明細!B389 | D58: =支出明細!D389 | E58: =支出明細!E389 | F58: 389
A59: =支出明細!A1844 | B59: =支出明細!C1844 | C59: =支出明細!B1844 | D59: =支出明細!D1844 | E59: =支出明細!E1844 | F59: 1845
A60: =支出明細!A583 | B60: =支出明細!C583 | C60: =支出明細!B583 | D60: =支出明細!D583 | E60: =支出明細!E583 | F60: 583
A61: =支出明細!A1444 | B61: =支出明細!C1444 | C61: =支出明細!B1444 | D61: =支出明細!D1444 | E61: =支出明細!E1444 | F61: 1444
A62: =支出明細!A911 | B62: =支出明細!C911 | C62: =支出明細!B911 | D62: =支出明細!D911 | E62: =支出明細!E911 | F62: 911
A63: =支出明細!A1277 | B63: =支出明細!C1277 | C63: =支出明細!B1277 | D63: =支出明細!D1277 | E63: =支出明細!E1277 | F63: 1277
A64: =支出明細!A1660 | B64: =支出明細!C1660 | C64: =支出明細!B1660 | D64: =支出明細!D1660 | E64: =支出明細!E1660 | F64: 1661
A65: =支出明細!A912 | B65: =支出明細!C912 | C65: =支出明細!B912 | D65: =支出明細!D912 | E65: =支出明細!E912 | F65: 912
A66: =支出明細!A1571 | B66: =支出明細!C1571 | C66: =支出明細!B1571 | D66: =支出明細!D1571 | E66: =支出明細!E1571 | F66: 1571
A67: =支出明細!A1505 | B67: =支出明細!C1505 | C67: =支出明細!B1505 | D67: =支出明細!D1505 | E67: =支出明細!E1505 | F67: 1505
A68: =支出明細!A222 | B68: =支出明細!C222 | C68: =支出明細!B222 | D68: =支出明細!D222 | E68: =支出明細!E222 | F68: 222
A69: =支出明細!A553 | B69: =支出明細!C553 | C69: =支出明細!B553 | D69: =支出明細!D553 | E69: =支出明細!E553 | F69: 553
A70: =支出明細!A664 | B70: =支出明細!C664 | C70: =支出明細!B664 | D70: =支出明細!D664 | E70: =支出明細!E664 | F70: 664
A71: =支出明細!A665 | B71: =支出明細!C665 | C71: =支出明細!B665 | D71: =支出明細!D665 | E71: =支出明細!E665 | F71: 665
A72: =支出明細!A688 | B72: =支出明細!C688 | C72: =支出明細!B688 | D72: =支出明細!D688 | E72: =支出明細!E688 | F72: 688
A73: =支出明細!A849 | B73: =支出明細!C849 | C73: =支出明細!B849 | D73: =支出明細!D849 | E73: =支出明細!E849 | F73: 849
A74: =支出明細!A1056 | B74: =支出明細!C1056 | C74: =支出明細!B1056 | D74: =支出明細!D1056 | E74: =支出明細!E1056 | F74: 1056
A75: =支出明細!A1057 | B75: =支出明細!C1057 | C75: =支出明細!B1057 | D75: =支出明細!D1057 | E75: =支出明細!E1057 | F75: 1057
A76: =支出明細!A1146 | B76: =支出明細!C1146 | C76: =支出明細!B1146 | D76: =支出明細!D1146 | E76: =支出明細!E1146 | F76: 1146
A77: =支出明細!A1275 | B77: =支出明細!C1275 | C77: =支出明細!B1275 | D77: =支出明細!D1275 | E77: =支出明細!E1275 | F77: 1275
A78: =支出明細!A1611 | B78: =支出明細!C1611 | C78: =支出明細!B1611 | D78: =支出明細!D1611 | E78: =支出明細!E1611 | F78: 1612
A79: =支出明細!A1612 | B79: =支出明細!C1612 | C79: =支出明細!B1612 | D79: =支出明細!D1612 | E79: =支出明細!E1612 | F79: 1613
A80: =支出明細!A132 | B80: =支出明細!C132 | C80: =支出明細!B132 | D80: =支出明細!D132 | E80: =支出明細!E132 | F80: 132
A81: =支出明細!A1083 | B81: =支出明細!C1083 | C81: =支出明細!B1083 | D81: =支出明細!D1083 | E81: =支出明細!E1083 | F81: 1083
A82: =支出明細!A1177 | B82: =支出明細!C1177 | C82: =支出明細!B1177 | D82: =支出明細!D1177 | E82: =支出明細!E1177 | F82: 1177
A83: =支出明細!A1613 | B83: =支出明細!C1613 | C83: =支出明細!B1613 | D83: =支出明細!D1613 | E83: =支出明細!E1613 | F83: 1614
A84: =支出明細!A1808 | B84: =支出明細!C1808 | C84: =支出明細!B1808 | D84: =支出明細!D1808 | E84: =支出明細!E1808 | F84: 1809
A85: =支出明細!A1054 | B85: =支出明細!C1054 | C85: =支出明細!B1054 | D85: =支出明細!D1054 | E85: =支出明細!E1054 | F85: 1054
A86: =支出明細!A1805 | B86: =支出明細!C1805 | C86: =支出明細!B1805 | D86: =支出明細!D1805 | E86: =支出明細!E1805 | F86: 1806
A87: =支出明細!A248 | B87: =支出明細!C248 | C87: =支出明細!B248 | D87: =支出明細!D248 | E87: =支出明細!E248 | F87: 248
A88: =支出明細!A852 | B88: =支出明細!C852 | C88: =支出明細!B852 | D88: =支出明細!D852 | E88: =支出明細!E852 | F88: 852
A89: =支出明細!A219 | B89: =支出明細!C219 | C89: =支出明細!B219 | D89: =支出明細!D219 | E89: =支出明細!E219 | F89: 219
A90: =支出明細!A1841 | B90: =支出明細!C1841 | C90: =支出明細!B1841 | D90: =支出明細!D1841 | E90: =支出明細!E1841 | F90: 1842
A91: =支出明細!A554 | B91: =支出明細!C554 | C91: =支出明細!B554 | D91: =支出明細!D554 | E91: =支出明細!E554 | F91: 554
A92: =支出明細!A1769 | B92: =支出明細!C1769 | C92: =支出明細!B1769 | D92: =支出明細!D1769 | E92: =支出明細!E1769 | F92: 1770
A93: =支出明細!A889 | B93: =支出明細!C889 | C93: =支出明細!B889 | D93: =支出明細!D889 | E93: =支出明細!E889 | F93: 889
A94: =支出明細!A1272 | B94: =支出明細!C1272 | C94: =支出明細!B1272 | D94: =支出明細!D1272 | E94: =支出明細!E1272 | F94: 1272
A95: =支出明細!A1273 | B95: =支出明細!C1273 | C95: =支出明細!B1273 | D95: =支出明細!D1273 | E95: =支出明細!E1273 | F95: 1273
A96: =支出明細!A130 | B96: =支出明細!C130 | C96: =支出明細!B130 | D96: =支出明細!D130 | E96: =支出明細!E130 | F96: 130
A97: =支出明細!A331 | B97: =支出明細!C331 | C97: =支出明細!B331 | D97: =支出明細!D331 | E97: =支出明細!E331 | F97: 331
A98: =支出明細!A301 | B98: =支出明細!C301 | C98: =支出明細!B301 | D98: =支出明細!D301 | E98: =支出明細!E301 | F98: 301
A99: =支出明細!A689 | B99: =支出明細!C689 | C99: =支出明細!B689 | D99: =支出明細!D689 | E99: =支出明細!E689 | F99: 689
A100: =支出明細!A690 | B100: =支出明細!C690 | C100: =支出明細!B690 | D100: =支出明細!D690 | E100: =支出明細!E690 | F100: 690
A101: =支出明細!A691 | B101: =支出明細!C691 | C101: =支出明細!B691 | D101: =支出明細!D691 | E101: =支出明細!E691 | F101: 691
A102: =支出明細!A741 | B102: =支出明細!C741 | C102: =支出明細!B741 | D102: =支出明細!D741 | E102: =支出明細!E741 | F102: 741
...

Sheet 帳戶餘額矩陣
A1: 帳戶 | B1: 2021-01 期末 | C1: 2021-02 期末 | D1: 2021-03 期末 | E1: 2021-04 期末 | F1: 2021-05 期末 | G1: 2021-06 期末 | H1: 2021-07 期末 | I1: 2021-08 期末 | J1: 2021-09 期末 | K1: 2021-10 期末 | L1: 2021-11 期末 | M1: 2021-12 期末 | N1: 2022-01 期末 | O1: 2022-02 期末 | P1: 2022-03 期末 | Q1: 2022-04 期末 | R1: 2022-05 期末 | S1: 2022-06 期末 | T1: 2022-07 期末 | U1: 2022-08 期末 | V1: 2022-09 期末 | W1: 2022-10 期末 | X1: 2022-11 期末 | Y1: 2022-12 期末 | Z1: 2023-01 期末 | AA1: 2023-02 期末 | AB1: 2023-03 期末 | AC1: 2023-04 期末 | AD1: 2023-05 期末 | AE1: 2023-06 期末 | AF1: 2023-07 期末 | AG1: 2023-08 期末 | AH1: 2023-09 期末 | AI1: 2023-10 期末 | AJ1: 2023-11 期末 | AK1: 2023-12 期末 | AL1: 2024-01 期末 | AM1: 2024-02 期末 | AN1: 2024-03 期末 | AO1: 2024-04 期末 | AP1: 2024-05 期末 | AQ1: 2024-06 期末 | AR1: 2024-07 期末 | AS1: 2024-08 期末 | AT1: 2024-09 期末 | AU1: 2024-10 期末 | AV1: 2024-11 期末 | AW1: 2024-12 期末 | AX1: 2025-01 期末 | AY1: 2025-02 期末 | AZ1: 2025-03 期末 | BA1: 2025-04 期末 | BB1: 2025-05 期末 | BC1: 2025-06 期末 | BD1: 2025-07 期末 | BE1: 2025-08 期末 | BF1: 2025-09 期末 | BG1: 2025-10 期末 | BH1: 2025-11 期末 | BI1: 2025-12 期末 | BJ1: 2026-01 期末 | BK1: 2026-02 期末 | BL1: 2026-03 期末 | BM1: 2026-04 期末
A2: 元大-充電樁 | BM2: 1751560
A3: 元大-管理費 | B3: 11050941 | C3: 9157051 | D3: 7997326 | E3: 9348204 | F3: 8771140 | G3: 7522776 | H3: 8848852 | I3: 8430866 | J3: 6877926 | K3: 8112288 | L3: 7031183 | M3: 6115928 | N3: 7160287 | O3: 6719611 | P3: 5702708 | Q3: 7546295 | R3: 7199409 | S3: 6315212 | T3: 8280329 | U3: 8136545 | V3: 7338105 | W3: 9132806 | X3: 8457053 | Y3: 7405360 | Z3: 9288384 | AA3: 8162372 | AB3: 7147349 | AC3: 8996801 | AD3: 8817812 | AE3: 7818200 | AF3: 9876163 | AG3: 9033289 | AH3: 8071947 | AI3: 10477719 | AJ3: 9827578 | AK3: 8359517 | AL3: 10772367 | AM3: 9961477 | AN3: 8747981 | AO3: 10507404 | AP3: 10127658 | AQ3: 8787799 | AR3: 10879125 | AS3: 10006791 | AT3: 8504284 | AU3: 10826821 | AV3: 9950090 | AW3: 8667153 | AX3: 9368331 | AY3: 10906768 | AZ3: 9730061 | BA3: 10365084 | BB3: 9995112 | BC3: 8727581 | BD3: 7159519 | BE3: 5426677 | BF3: 3062620 | BG3: 3055046 | BH3: 2491599 | BI3: 1682704 | BJ3: 2663490 | BK3: 1796297 | BL3: 1467895 | BM3: 4308271
A4: 元大-管理費(裝保金暫收款) | BM4: 80000
A5: 元大-電梯 | B5: 2225479 | C5: 2277084 | D5: 2328175 | E5: 2379383 | F5: 2430552 | G5: 2481785 | H5: 2532954 | I5: 2584162 | J5: 2635370 | K5: 2686539 | L5: 2737747 | M5: 2788956 | N5: 2840164 | O5: 2513372 | P5: 2564463 | Q5: 2615671 | R5: 2666840 | S5: 2718131 | T5: 2769300 | U5: 2820508 | V5: 2871716 | W5: 2922885 | X5: 2974093 | Y5: 3026380 | Z5: 3077588 | AA5: 2663796 | AB5: 2715764 | AC5: 2767942 | AD5: 2820050 | AE5: 2874626 | AF5: 2926734 | AG5: 2978912 | AH5: 2511090 | AI5: 2563198 | AJ5: 2615376 | AK5: 2670019 | AL5: 2722197 | AM5: 2254375 | AN5: 2306592 | AO5: 2358962 | AP5: 2411255 | AQ5: 2465548 | AR5: 2517841 | AS5: 2570211 | AT5: 2622581 | AU5: 2154874 | AV5: 2209537 | AW5: 2213973 | AX5: 2313973 | AY5: 2316343 | AZ5: 2368656 | BA5: 2421217 | BB5: 910548 | BC5: 912597 | BD5: 912597 | BM5: 1445251
A6: 台銀-公共基金(定存) | B6: 5915617 | C6: 5918333 | D6: 5921049 | E6: 5923765 | F6: 5926481 | G6: 5929580 | H6: 5932296 | I6: 5935012 | J6: 5937728 | K6: 5940444 | L6: 5943160 | M6: 5946265 | N6: 5948981 | O6: 5951697 | P6: 5954413 | Q6: 5957685 | R6: 5961237 | S6: 5965383 | T6: 5969211 | U6: 5973179 | V6: 5977147 | W6: 5981307 | X6: 5985691 | Y6: 5992704 | Z6: 5997392 | AA6: 6002192 | AB6: 6006992 | AC6: 6011988 | AD6: 6017204 | AE6: 6027566 | AF6: 6032782 | AG6: 6037998 | AH6: 6043214 | AI6: 6048430 | AJ6: 6053646 | AK6: 6064801 | AL6: 6070017 | AM6: 6075233 | AN6: 6080449 | AO6: 6085889 | AP6: 6091521 | AQ6: 6103831 | AR6: 6109463 | AS6: 6115095 | AT6: 6120727 | AU6: 6126359 | AV6: 6131991 | AW6: 6145116 | AX6: 6150748 | AY6: 6156380 | AZ6: 6162012 | BA6: 6167644 | BB6: 6173276 | BC6: 6186505 | BD6: 4000000 | BE6: 4000000 | BF6: 4000000 | BG6: 4000000 | BH6: 4000000 | BI6: 4000000 | BJ6: 4000000 | BK6: 4000000 | BL6: 4000000 | BM6: 4000000
A7: 台銀-活存 | BE7: 2197769 | BF7: 2203401 | BG7: 2209033 | BH7: 2214665 | BI7: 2228082 | BJ7: 2233714 | BK7: 2239346 | BL7: 2244978 | BM7: 11224
A8: 應收-AED押金 | B8: 10798 | C8: 20000 | D8: 20000 | E8: 20000 | F8: 20000 | G8: 20000 | H8: 20000 | I8: 4000 | J8: 4000 | K8: 4000 | L8: 4000 | M8: 4000 | N8: 4000 | O8: 4000 | P8: 4000 | Q8: 4000 | R8: 4000 | S8: 4000 | T8: 4000 | U8: 4000 | V8: 4000 | W8: 4000 | X8: 4000 | Y8: 4000 | Z8: 4000 | AA8: 4000 | AB8: 4000 | AC8: 4000 | AD8: 4000 | AE8: 4000 | AF8: 4000 | AG8: 4000 | AH8: 4000 | AI8: 4000 | AJ8: 4000 | AK8: 4000 | AL8: 4000 | AM8: 4000 | AN8: 4000 | AO8: 4000 | AP8: 4000 | AQ8: 4000 | AR8: 4000 | AS8: 4000 | AT8: 4000 | AU8: 4000 | AV8: 4000 | AW8: 4000 | AX8: 4000 | AY8: 4000 | AZ8: 4000 | BA8: 4000 | BB8: 4000 | BC8: 4000 | BD8: 10000 | BE8: 10000 | BF8: 10000 | BG8: 10000 | BH8: 10000 | BI8: 10000 | BJ8: 10000 | BK8: 10000 | BL8: 10000 | BM8: 10000
A9: 零用金 | BM9: 17444
A10: 全帳戶月末合計 | B10: 19202835 | C10: 17372468 | D10: 16266550 | E10: 17671352 | F10: 17148173 | G10: 15954141 | H10: 17334102 | I10: 16954040 | J10: 15455024 | K10: 16743271 | L10: 15716090 | M10: 14855149 | N10: 15953432 | O10: 15188680 | P10: 14225584 | Q10: 16123651 | R10: 15831486 | S10: 15002726 | T10: 17022840 | U10: 16934232 | V10: 16190968 | W10: 18040998 | X10: 17420837 | Y10: 16428444 | Z10: 18367364 | AA10: 16832360 | AB10: 15874105 | AC10: 17780731 | AD10: 17659066 | AE10: 16724392 | AF10: 18839679 | AG10: 18054199 | AH10: 16630251 | AI10: 19093347 | AJ10: 18500600 | AK10: 17098337 | AL10: 19568581 | AM10: 18295085 | AN10: 17139022 | AO10: 18956255 | AP10: 18634434 | AQ10: 17361178 | AR10: 19510429 | AS10: 18696097 | AT10: 17251592 | AU10: 19112054 | AV10: 18295618 | AW10: 17030242 | AX10: 17837052 | AY10: 19383491 | AZ10: 18264729 | BA10: 18957945 | BB10: 17082936 | BC10: 15830683 | BD10: 12082116 | BE10: 11634446 | BF10: 9276021 | BG10: 9274079 | BH10: 8716264 | BI10: 7920786 | BJ10: 8907204 | BK10: 8045643 | BL10: 7722873 | BM10: 11623750

Sheet 帳戶月度明細
A1: 月份 | B1: 帳戶 | C1: 上期餘額 | D1: 本月收入 | E1: 本月支出 | F1: 期末餘額
A2: 2021-01 | B2: 元大-管理費 | C2: 10096540 | D2: 954401 | E2: 0 | F2: 11050941
A3: 2021-01 | B3: 台銀-公共基金(定存) | C3: 5912901 | D3: 2716 | E3: 0 | F3: 5915617
A4: 2021-01 | B4: 元大-電梯 | C4: 2173874 | D4: 51605 | E4: 0 | F4: 2225479
A5: 2021-01 | B5: 應收-AED押金 | C5: 15923 | D5: 0 | E5: 5125 | F5: 10798
A6: 2021-01 | B6: ↳ 2021-01 小計 (4 帳) | C6: 18199238 | D6: 1008722 | E6: 5125 | F6: 19202835
A7: 2021-02 | B7: 元大-管理費 | C7: 11050941 | D7: 0 | E7: 1893890 | F7: 9157051
A8: 2021-02 | B8: 台銀-公共基金(定存) | C8: 5915617 | D8: 2716 | E8: 0 | F8: 5918333
A9: 2021-02 | B9: 元大-電梯 | C9: 2225479 | D9: 51605 | E9: 0 | F9: 2277084
A10: 2021-02 | B10: 應收-AED押金 | C10: 10798 | D10: 9202 | E10: 0 | F10: 20000
A11: 2021-02 | B11: ↳ 2021-02 小計 (4 帳) | C11: 19202835 | D11: 63523 | E11: 1893890 | F11: 17372468
A12: 2021-03 | B12: 元大-管理費 | C12: 9157051 | D12: 0 | E12: 1159725 | F12: 7997326
A13: 2021-03 | B13: 台銀-公共基金(定存) | C13: 5918333 | D13: 2716 | E13: 0 | F13: 5921049
... A325: 2026-04 | B325: ↳ 2026-04 小計 (8 帳) | C325: 11025447 | D325: 5707536 | E325: 5109233 | F325: 11623750

Sheet 專款明細
A1: 月份 | B1: 專款 | C1: 項目類型 | D1: 科目 / 摘要 | E1: 金額
A2: 2022-03 | B2: 充電樁 | C2: 上期餘額 | E2: 0
A3: 2022-03 | B3: 充電樁 | C3: 收入 | D3: 自111年Q2季起 每季應收管理費$3,857,907 | E3: 2
A4: 2022-03 | B4: 充電樁 | C4: 本月小計 | D4: 收 2 / 支 0 | E4: 2
A5: 2022-03 | B5: 電梯 | C5: 上期餘額 | E5: 0
A6: 2022-03 | B6: 電梯 | C6: 收入 | D6: 自111年Q2季起 每季應收管理費$3,857,907 | E6: 2
A7: 2022-03 | B7: 電梯 | C7: 本月小計 | D7: 收 2 / 支 0 | E7: 2
A8: 2022-04 | B8: 充電樁 | C8: 上期餘額 | E8: 0
A9: 2022-04 | B9: 充電樁 | C9: 收入 | D9: 自111年Q2季起 每季應收管理費$3,857,907 | E9: 1
A10: 2022-04 | B10: 充電樁 | C10: 本月小計 | D10: 收 1 / 支 0 | E10: 1
A11: 2022-04 | B11: 電梯 | C11: 上期餘額 | E11: 0
A12: 2022-04 | B12: 電梯 | C12: 收入 | D12: 自111年Q2季起 每季應收管理費$3,857,907 | E12: 1
A13: 2022-04 | B13: 電梯 | C13: 本月小計 | D13: 收 1 / 支 0 | E13: 1
A14: 2022-05 | B14: 充電樁 | C14: 上期餘額 | E14: 0
A15: 2022-05 | B15: 充電樁 | C15: 收入 | D15: 自111年Q2季起 每季應收管理費$3,857,907 | E15: 1
A16: 2022-05 | B16: 充電樁 | C16: 本月小計 | D16: 收 1 / 支 0 | E16: 1
A17: 2022-05 | B17: 電梯 | C17: 上期餘額 | E17: 0
A18: 2022-05 | B18: 電梯 | C18: 收入 | D18: 自111年Q2季起 每季應收管理費$3,857,907 | E18: 1
A19: 2022-05 | B19: 電梯 | C19: 本月小計 | D19: 收 1 / 支 0 | E19: 1
A20: 2022-06 | B20: 充電樁 | C20: 上期餘額 | E20: 4145183
A21: 2022-06 | B21: 充電樁 | C21: 收入 | D21: 自111年Q2季起 每季應收管理費$3,857,907 | E21: 12
A22: 2022-06 | B22: 充電樁 | C22: 本月小計 | D22: 收 12 / 支 0 | E22: 4145195
A23: 2022-06 | B23: 電梯 | C23: 上期餘額 | E23: 4145183
A24: 2022-06 | B24: 電梯 | C24: 收入 | D24: 自111年Q2季起 每季應收管理費$3,857,907 | E24: 12
A25: 2022-06 | B25: 電梯 | C25: 本月小計 | D25: 收 12 / 支 0 | E25: 4145195
A26: 2022-07 | B26: 充電樁 | C26: 上期餘額 | E26: 4129086
A27: 2022-07 | B27: 充電樁 | C27: 收入 | D27: 自111年Q2季起 每季應收管理費$3,857,907 | E27: 4
A28: 2022-07 | B28: 充電樁 | C28: 本月小計 | D28: 收 4 / 支 0 | E28: 4129090
A29: 2022-07 | B29: 電梯 | C29: 上期餘額 | E29: 4129086
A30: 2022-07 | B30: 電梯 | C30: 收入 | D30: 自111年Q2季起 每季應收管理費$3,857,907 | E30: 4
A31: 2022-07 | B31: 電梯 | C31: 本月小計 | D31: 收 4 / 支 0 | E31: 4129090
A32: 2022-08 | B32: 充電樁 | C32: 上期餘額 | E32: 4129086
A33: 2022-08 | B33: 充電樁 | C33: 本月小計 | D33: 收 0 / 支 0 | E33: 4129086
A34: 2022-08 | B34: 電梯 | C34: 上期餘額 | E34: 4129086
A35: 2022-08 | B35: 電梯 | C35: 本月小計 | D35: 收 0 / 支 0 | E35: 4129086
A36: 2022-09 | B36: 充電樁 | C36: 上期餘額 | E36: 4129086
A37: 2022-09 | B37: 充電樁 | C37: 本月小計 | D37: 收 0 / 支 0 | E37: 4129086
A38: 2022-09 | B38: 電梯 | C38: 上期餘額 | E38: 4129086
A39: 2022-09 | B39: 電梯 | C39: 本月小計 | D39: 收 0 / 支 0 | E39: 4129086
A40: 2022-10 | B40: 充電樁 | C40: 上期餘額 | E40: 4239086
A41: 2022-10 | B41: 充電樁 | C41: 本月小計 | D41: 收 0 / 支 0 | E41: 4239086
A42: 2022-10 | B42: 電梯 | C42: 上期餘額 | E42: 4239086
A43: 2022-10 | B43: 電梯 | C43: 本月小計 | D43: 收 0 / 支 0 | E43: 4239086
A44: 2022-11 | B44: 充電樁 | C44: 上期餘額 | E44: 4399086
A45: 2022-11 | B45: 充電樁 | C45: 本月小計 | D45: 收 0 / 支 0 | E45: 4399086
A46: 2022-11 | B46: 電梯 | C46: 上期餘額 | E46: 4399086
A47: 2022-11 | B47: 電梯 | C47: 本月小計 | D47: 收 0 / 支 0 | E47: 4399086
A48: 2022-12 | B48: 充電樁 | C48: 上期餘額 | E48: 4699086
A49: 2022-12 | B49: 充電樁 | C49: 本月小計 | D49: 收 0 / 支 0 | E49: 4699086
A50: 2022-12 | B50: 電梯 | C50: 上期餘額 | E50: 4699086
A51: 2022-12 | B51: 電梯 | C51: 本月小計 | D51: 收 0 / 支 0 | E51: 4699086
A52: 2023-01 | B52: 充電樁 | C52: 上期餘額 | E52: 4853668
A53: 2023-01 | B53: 充電樁 | C53: 本月小計 | D53: 收 0 / 支 0 | E53: 4853668
A54: 2023-01 | B54: 電梯 | C54: 上期餘額 | E54: 4853668
A55: 2023-01 | B55: 電梯 | C55: 本月小計 | D55: 收 0 / 支 0 | E55: 4853668
A56: 2023-02 | B56: 充電樁 | C56: 上期餘額 | E56: 4903668
A57: 2023-02 | B57: 充電樁 | C57: 本月小計 | D57: 收 0 / 支 0 | E57: 4903668
A58: 2023-02 | B58: 電梯 | C58: 上期餘額 | E58: 4903668
A59: 2023-02 | B59: 電梯 | C59: 本月小計 | D59: 收 0 / 支 0 | E59: 4903668
A60: 2023-03 | B60: 充電樁 | C60: 上期餘額 | E60: 4903668
A61: 2023-03 | B61: 充電樁 | C61: 收入 | D61: 戶數 | E61: 417
A62: 2023-03 | B62: 充電樁 | C62: 收入 | D62: 未繳金額 | E62: 3846441
A63: 2023-03 | B63: 充電樁 | C63: 本月小計 | D63: 收 3,846,858 / 支 0 | E63: 8750526
A64: 2023-03 | B64: 電梯 | C64: 上期餘額 | E64: 4903668
A65: 2023-03 | B65: 電梯 | C65: 收入 | D65: 戶數 | E65: 417
A66: 2023-03 | B66: 電梯 | C66: 收入 | D66: 未繳金額 | E66: 3846441
A67: 2023-03 | B67: 電梯 | C67: 本月小計 | D67: 收 3,846,858 / 支 0 | E67: 8750526
A68: 2023-04 | B68: 充電樁 | C68: 上期餘額 | E68: 4513668
A69: 2023-04 | B69: 充電樁 | C69: 收入 | D69: 戶數 | E69: 106
A70: 2023-04 | B70: 充電樁 | C70: 收入 | D70: 未繳金額 | E70: 957012
A71: 2023-04 | B71: 充電樁 | C71: 本月小計 | D71: 收 957,118 / 支 0 | E71: 5470786
A72: 2023-04 | B72: 電梯 | C72: 上期餘額 | E72: 4513668
A73: 2023-04 | B73: 電梯 | C73: 收入 | D73: 戶數 | E73: 106
A74: 2023-04 | B74: 電梯 | C74: 收入 | D74: 未繳金額 | E74: 957012
A75: 2023-04 | B75: 電梯 | C75: 本月小計 | D75: 收 957,118 / 支 0 | E75: 5470786
A76: 2023-05 | B76: 充電樁 | C76: 上期餘額 | E76: 4623668
A77: 2023-05 | B77: 充電樁 | C77: 收入 | D77: 戶數 | E77: 16
A78: 2023-05 | B78: 充電樁 | C78: 收入 | D78: 未繳金額 | E78: 137757
A79: 2023-05 | B79: 充電樁 | C79: 本月小計 | D79: 收 137,773 / 支 0 | E79: 4761441
A80: 2023-05 | B80: 電梯 | C80: 上期餘額 | E80: 4623668
A81: 2023-05 | B81: 電梯 | C81: 收入 | D81: 戶數 | E81: 16
A82: 2023-05 | B82: 電梯 | C82: 收入 | D82: 未繳金額 | E82: 137757
A83: 2023-05 | B83: 電梯 | C83: 本月小計 | D83: 收 137,773 / 支 0 | E83: 4761441
A84: 2023-06 | B84: 充電樁 | C84: 上期餘額 | E84: 4668784
A85: 2023-06 | B85: 充電樁 | C85: 收入 | D85: 戶數 | E85: 5
A86: 2023-06 | B86: 充電樁 | C86: 收入 | D86: 未繳金額 | E86: 42063
A87: 2023-06 | B87: 充電樁 | C87: 本月小計 | D87: 收 42,068 / 支 0 | E87: 4710852
A88: 2023-06 | B88: 電梯 | C88: 上期餘額 | E88: 4668784
A89: 2023-06 | B89: 電梯 | C89: 收入 | D89: 戶數 | E89: 5
A90: 2023-06 | B90: 電梯 | C90: 收入 | D90: 未繳金額 | E90: 42063
A91: 2023-06 | B91: 電梯 | C91: 本月小計 | D91: 收 42,068 / 支 0 | E91: 4710852
A92: 2023-07 | B92: 充電樁 | C92: 上期餘額 | E92: 1622880
A93: 2023-07 | B93: 充電樁 | C93: 收入 | D93: 戶數 | E93: 80
A94: 2023-07 | B94: 充電樁 | C94: 收入 | D94: 未繳金額 | E94: 726183
A95: 2023-07 | B95: 充電樁 | C95: 本月小計 | D95: 收 726,263 / 支 0 | E95: 2349143
A96: 2023-07 | B96: 電梯 | C96: 上期餘額 | E96: 1622880
A97: 2023-07 | B97: 電梯 | C97: 收入 | D97: 戶數 | E97: 80
A98: 2023-07 | B98: 電梯 | C98: 收入 | D98: 未繳金額 | E98: 726183
A99: 2023-07 | B99: 電梯 | C99: 本月小計 | D99: 收 726,263 / 支 0 | E99: 2349143
A100: 2023-08 | B100: 充電樁 | C100: 上期餘額 | E100: 1164655
...

Sheet 暫收款明細
A1: 月份 | B1: 類型 | C1: 日期 | D1: 戶別 | E1: 金額
A2: 2021-02 | B2: 收暫收 | C2: 2021-02-17 | D2: Q23 | E2: 20000
A3: 2021-02 | B3: 退暫收 | D3: H4 | E3: 80000
A4: 2021-02 | B4: 收暫收 | C4: 2021-02-25 | D4: K17 | E4: 20000
A5: 2021-02 | B5: 收暫收 | C5: 總計 | E5: 40000
A6: 2021-02 | B6: 收暫收 | C6: 6000000 | E6: 3157051
A7: 2021-02 | B7: 退暫收 | E7: 17382468
A8: 2021-02 | B8: 收暫收 | C8: 4000000 | E8: 1915617
A9: 2021-02 | B9: 收暫收 | C9: 1800000 | E9: 475479
A10: 2023-12 | B10: 收暫收 | C10: 4 | D10: 11 | E10: 414
A11: 2023-12 | B11: 收暫收 | C11: 28437 | D11: 97723 | E11: 3825979
A12: 2024-01 | B12: 收暫收 | C12: Q1 | E12: 40
A13: 2024-01 | B13: 收暫收 | C13: 342471 | E13: 350247
A14: 2024-02 | B14: 收暫收 | C14: Q1 | E14: 8
A15: 2024-02 | B15: 收暫收 | C15: 66411 | E15: 74187
A16: 2024-03 | B16: 收暫收 | C16: Q2 | E16: 4
A17: 2024-03 | B17: 收暫收 | E17: 29271
A18: 2024-04 | B18: 收暫收 | C18: Q2 | E18: 91
A19: 2024-04 | B19: 收暫收 | C19: 802296 | E19: 815361
A20: 2024-05 | B20: 收暫收 | C20: 2 | E20: 16
A21: 2024-05 | B21: 收暫收 | C21: 13065 | E21: 137088
A22: 2024-06 | B22: 收暫收 | C22: 2 | E22: 5
A23: 2024-06 | B23: 收暫收 | C23: 13065 | E23: 36102
A24: 2024-07 | B24: 收暫收 | C24: 57 | E24: 59
A25: 2024-07 | B25: 收暫收 | C25: 516762 | E25: 532284
A26: 2025-06 | B26: 收暫收 | C26: S11 | D26: 2025-06-27 00:00:00 | E26: 80000
A27: 2025-06 | B27: 退暫收 | E27: 140000
A28: 2025-06 | B28: 收暫收 | C28: 總計 | E28: 80000
A29: 2025-06 | B29: 收暫收 | C29: 5000000 | E29: 3727581
A30: 2025-06 | B30: 退暫收 | E30: 15860683
A31: 2025-06 | B31: 收暫收 | C31: 4000000 | E31: 2173276
A32: 2025-08 | B32: 收暫收 | C32: 2025-08-14 | D32: B13 | E32: 20000
A33: 2025-08 | B33: 退暫收 | E33: 160000
A34: 2025-08 | B34: 收暫收 | C34: 總計 | E34: 20000
A35: 2025-08 | B35: 收暫收 | C35: 45 | D35: 33 | E35: 66
A36: 2025-09 | B36: 收暫收 | C36: 2025-09-11 | D36: S8 | E36: 80000
A37: 2025-09 | B37: 退暫收 | E37: 220000
A38: 2025-09 | B38: 收暫收 | C38: 總計 | E38: 80000
A39: 2025-09 | B39: 收暫收 | C39: 45 | D39: 33 | E39: 54
A40: 2025-10 | B40: 退暫收 | E40: 200000
A41: 2025-10 | B41: 收暫收 | C41: 15 | D41: 37 | E41: 45
A42: 2025-11 | B42: 收暫收 | C42: 2025-11-10 | D42: K4 | E42: 20000
A43: 2025-11 | B43: 退暫收 | E43: 260000
A44: 2025-11 | B44: 收暫收 | C44: 2025-11-20 | D44: G5 | E44: 20000
A45: 2025-11 | B45: 收暫收 | C45: 2025-11-24 | D45: J15 | E45: 20000
A46: 2025-11 | B46: 收暫收 | C46: 總計 | E46: 60000
A47: 2025-11 | B47: 收暫收 | C47: 15 | D47: 37 | E47: 43
A48: 2025-12 | B48: 收暫收 | C48: 2026-12-03 | D48: P12 | E48: 20000
A49: 2025-12 | B49: 退暫收 | E49: 200000
A50: 2025-12 | B50: 收暫收 | C50: 總計 | E50: 20000
A51: 2025-12 | B51: 收暫收 | D51: 34 | E51: 26
A52: 2026-01 | B52: 退暫收 | E52: 200000
A53: 2026-01 | B53: 收暫收 | C53: 14 | D53: 17 | E53: 121
A54: 2026-02 | B54: 退暫收 | E54: 140000
A55: 2026-02 | B55: 收暫收 | C55: 3 | D55: 8 | E55: 28
A56: 2026-02 | B56: 收暫收 | C56: 23568 | D56: 83391 | E56: 205128
A57: 2026-03 | B57: 退暫收 | E57: 140000
A58: 2026-03 | B58: 收暫收 | C58: 3 | D58: 8 | E58: 27
A59: 2026-03 | B59: 收暫收 | C59: 23568 | D59: 83391 | E59: 204279
A60: 2026-04 | B60: 收暫收 | C60: 2026-04-20 | D60: D6 | E60: 20000
A61: 2026-04 | B61: 收暫收 | C61: 總計 | E61: 20000
A62: 2026-04 | B62: 收暫收 | C62: 3 | D62: 5 | E62: 22
A63: 2026-04 | B63: 收暫收 | C63: 23568 | D63: 48636 | E63: 134172
A65: 📝 本期收暫收合計：NT$ 18,434,171 ／ 退暫收合計：NT$ 34,983,151 ／ 淨增加：NT$ -16,548,980

Sheet 管理費未繳統計
A1: 月份 | B1: 季別 | C1: 未繳戶數 | D1: 未繳金額
A2: 2021-01 | B2: Q1 | C2: 0 | D2: 0
A3: 2021-01 | B3: Q2 | C3: 0 | D3: 0
A4: 2021-01 | B4: Q3 | C4: 1 | D4: 4350
A5: 2021-01 | B5: Q4 | C5: 1 | D5: 4350
A6: 2021-01 | B6: Q1 | C6: 125 | D6: 924324
A7: 2021-02 | B7: Q1 | C7: 8 | D7: 62322
A8: 2021-02 | B8: Q2 | C8: 0 | D8: 0
A9: 2021-02 | B9: Q3 | C9: 0 | D9: 0
A10: 2021-02 | B10: Q4 | C10: 0 | D10: 0
A11: 2021-03 | B11: Q1 | C11: 5 | D11: 33690
A12: 2021-03 | B12: Q2 | C12: 412 | D12: 3036234
A13: 2021-03 | B13: Q3 | C13: 0 | D13: 0
... A214: 2026-04 | B214: Q2 | C214: 51 | D214: 576294

Sheet 議案-主鋼索更換
A1: 議案 — 電梯主鋼索更換歷史 (10 次)
A2: 資料來源: 電梯專戶明細 sheet (世界島電梯專戶(威) 0413-僅電梯專戶表格.xlsx)
A4: ◆ 統計
A5: 總次數 | B5: 10 次
A6: 累計支出 | B6: NT$ 4,725,550
A7: 平均每次 | B7: NT$ 472,555
A8: 時間區間 | B8: 2020-10-06 ~ 2025-07-21 (橫跨 6 年)
A9: 峰值年度 | B9: 2025 年: 4 條 ($2,080,000)
A11: ◆ 逐筆明細 (依時間順序)
A12: # | B12: 民國日期 | C12: 西元日期 | D12: 主鋼索編號 | E12: 金額 | F12: 備註
A13: 1 | B13: 109.10.06 | C13: 2020-10-06 | D13: 主鋼索1 | E13: 242550 | F13: 首次更換，金額較低 (可能為小範圍維修而非全套)
A14: 2 | B14: 111.02.24 | C14: 2022-02-24 | D14: 主鋼索3 | E14: 378000 | F14: 同步整理檔已記錄 (鑫禾機電)
A15: 3 | B15: 112.02.24 | C15: 2023-02-24 | D15: 主鋼索2 | E15: 465000 | F15: 次年更換編號 2
A16: 4 | B16: 112.09.27 | C16: 2023-09-27 | D16: 主鋼索8 | E16: 520000 | F16: 單價跳升至 52 萬
A17: 5 | B17: 113.02.26 | C17: 2024-02-26 | D17: 主鋼索6 | E17: 520000
A18: 6 | B18: 113.10.28 | C18: 2024-10-28 | D18: 主鋼索10 | E18: 520000 | F18: ⚠️ 物業交接前最後一筆
A19: 7 | B19: 114.05.02 | C19: 2025-05-02 | D19: 主鋼索5 | E19: 520000 | F19: 🔴 同日 3 條 (5、4、7)，合計 $1,560,000，可能配合 解定存 $1.8M 進行
A20: 8 | B20: 114.05.02 | C20: 2025-05-02 | D20: 主鋼索4 | E20: 520000 | F20: 🔴 同上
A21: 9 | B21: 114.05.02 | C21: 2025-05-02 | D21: 主鋼索7 | E21: 520000 | F21: 🔴 同上
A22: 10 | B22: 114.07.21 | C22: 2025-07-21 | D22: 主鋼索9 | E22: 520000 | F22: 整理檔 2025-07 元大-電梯 變動漏記 — 帳上仍顯示 912,597
A23: 合計 | D23: 10 次 | E23: 4725550
A25: ◆ 觀察與建議
A26: • 主鋼索更換從 2020 年首次後，逐漸密集。2022/2023/2024 每年 1-3 條，2025 年 5 月一次 3 條。
A27: • 平均每年從電梯專戶撥出 ~$800K 用於主鋼索更換 (2022 後)，遠超月撥款 50K-100K 的累積速度。
A28: • 2025-05 同日 3 條 + 2025-07 1 條 = 共 4 條 ($2.08M)，與 解定存 1,799,331 時間吻合 — 可能是規劃性維修。
A29: • 期末活儲 1,345,251 (2026-03)，定存已全部解約。資金水位需注意。
A30: • 整理檔 2025-07 元大-電梯 變動漏記 NT$ 320,000 (該補入)。

Sheet 電梯專戶明細
A1: 民國日期 | B1: 西元日期 | C1: 月份 | D1: 收入 | E1: 支出 | F1: 餘額 | G1: 說明 | H1: 分類
A2: 108.04.12 | B2: 2019-04-12 | C2: 2019-04 | D2: 50000 | F2: 50000 | G2: 108/04管理費撥款電梯專戶 | H2: 管理費撥款
A3: 108.04.12 | B3: 2019-04-12 | C3: 2019-04 | D3: 1250000 | F3: 1300000 | G3: 昌禾提撥款 | H3: 昌禾初始提撥
A4: 108.05.09 | B4: 2019-05-09 | C4: 2019-05 | D4: 50000 | F4: 1350000 | G4: 108/05管理費撥款電梯專戶 | H4: 管理費撥款
A5: 108.06.04 | B5: 2019-06-04 | C5: 2019-06 | D5: 50000 | F5: 1400000 | G5: 108/06管理費撥款電梯專戶 | H5: 管理費撥款
A6: 108.06.21 | B6: 2019-06-21 | C6: 2019-06 | D6: 129 | F6: 1400129 | G6: 存款息 | H6: 存款利息
A7: 108.07.08 | B7: 2019-07-08 | C7: 2019-07 | D7: 50000 | F7: 1450129 | G7: 108/07管理費撥款電梯專戶 | H7: 管理費撥款
A8: 108.07.09 | B8: 2019-07-09 | C8: 2019-07 | D8: 100000 | F8: 1550129 | G8: 108/07管理費重複撥款電梯專戶 | H8: 其他
A9: 108.08.06 | B9: 2019-08-06 | C9: 2019-08 | D9: 50000 | F9: 1600129 | G9: 108/08管理費撥款電梯專戶 | H9: 管理費撥款
A10: 108.09.09 | B10: 2019-09-09 | C10: 2019-09 | D10: 50000 | F10: 1650129 | G10: 108/09管理費撥款電梯專戶 | H10: 管理費撥款
A11: 108.10.04 | B11: 2019-10-04 | C11: 2019-10 | D11: 50000 | F11: 1700129 | G11: 108/10管理費撥款電梯專戶 | H11: 管理費撥款
A12: 108.11.08 | B12: 2019-11-08 | C12: 2019-11 | D12: 50000 | F12: 1750129 | G12: 108/11管理費撥款電梯專戶 | H12: 管理費撥款
A13: 108.12.10 | B13: 2019-12-10 | C13: 2019-12 | D13: 50000 | F13: 1800129 | G13: 108/12管理費撥款電梯專戶 | H13: 管理費撥款
... A16: 109.01.21 | B16: 2020-01-21 | C16: 2020-01 | D16: 50000 | F16: 1900539 | G16: 109/02管理費撥款電梯專戶 | H16: 管理費撥款
A17: 109.02.04 | B17: 2020-02-04 | C17: 2020-02 | E17: 1800000 | F17: 100539 | G17: 轉定存 | H17: 轉定存
A18: 109.03.04 | B18: 2020-03-04 | C18: 2020-03 | D18: 1502 | F18: 102041 | G18: 存款息 | H18: 存款利息
A19: 109.03.06 | B19: 2020-03-06 | C19: 2020-03 | D19: 50000 | F19: 152041 | G19: 109/03管理費撥款電梯專戶 | H19: 管理費撥款
A20: 109.04.06 | B20: 2020-04-06 | C20: 2020-04 | D20: 1605 | F20: 153646 | G20: 存款息 | H20: 存款利息
A21: 109.04.07 | B21: 2020-04-07 | C21: 2020-04 | D21: 50000 | F21: 203646 | G21: 109/04管理費撥款電梯專戶 | H21: 管理費撥款
A22: 109.05.04 | B22: 2020-05-04 | C22: 2020-05 | D22: 1553 | F22: 205199 | G22: 存款息 | H22: 存款利息
A23: 109.05.04 | B23: 2020-05-04 | C23: 2020-05 | D23: 50000 | F23: 255199 | G23: 109/05管理費撥款電梯專戶 | H23: 管理費撥款
A24: 109.06.01 | B24: 2020-06-01 | C24: 2020-06 | D24: 50000 | F24: 305199 | G24: 109/06管理費撥款電梯專戶 | H24: 管理費撥款
A25: 109.06.04 | B25: 2020-06-04 | C25: 2020-06 | D25: 1605 | F25: 306804 | G25: 存款息 | H25: 存款利息
A26: 109.06.21 | B26: 2020-06-21 | C26: 2020-06 | D26: 128 | F26: 306932 | G26: 存款息 | H26: 存款利息
A27: 109.07.06 | B27: 2020-07-06 | C27: 2020-07 | D27: 1553 | F27: 308485 | G27: 存款息 | H27: 存款利息
A28: 109.07.08 | B28: 2020-07-08 | C28: 2020-07 | D28: 50000 | F28: 358485 | G28: 109/07管理費撥款電梯專戶 | H28: 管理費撥款
A29: 109.08.04 | B29: 2020-08-04 | C29: 2020-08 | D29: 1605 | F29: 360090 | G29: 存款息 | H29: 存款利息
... A33: 109.10.05 | B33: 2020-10-05 | C33: 2020-10 | D33: 1553 | F33: 463248 | G33: 存款息 | H33: 存款利息
A34: 109.10.06 | B34: 2020-10-06 | C34: 2020-10 | E34: 242550 | F34: 220698 | G34: 更換主鋼索1 | H34: 主鋼索更換
A35: 109.10.06 | B35: 2020-10-06 | C35: 2020-10 | D35: 50000 | F35: 270698 | G35: 109/10管理費撥款電梯專戶 | H35: 管理費撥款
A36: 109.11.04 | B36: 2020-11-04 | C36: 2020-11 | D36: 1605 | F36: 272303 | G36: 存款息 | H36: 存款利息
A37: 109.11.04 | B37: 2020-11-04 | C37: 2020-11 | D37: 50000 | F37: 322303 | G37: 109/11管理費撥款電梯專戶 | H37: 管理費撥款
A38: 109.12.04 | B38: 2020-12-04 | C38: 2020-12 | D38: 1553 | F38: 323856 | G38: 存款息 | H38: 存款利息
A39: 109.12.04 | B39: 2020-12-04 | C39: 2020-12 | D39: 50000 | F39: 373856 | G39: 109/12管理費撥款電梯專戶 | H39: 管理費撥款
A40: 109.12.21 | B40: 2020-12-21 | C40: 2020-12 | D40: 18 | F40: 373874 | G40: 存款息 | H40: 存款利息
A41: 110.01.04 | B41: 2021-01-04 | C41: 2021-01 | D41: 1605 | F41: 375479 | G41: 存款息 | H41: 存款利息
A42: 110.01.04 | B42: 2021-01-04 | C42: 2021-01 | D42: 50000 | F42: 425479 | G42: 110/01管理費撥款電梯專戶 | H42: 管理費撥款
A43: 110.02.01 | B43: 2021-02-01 | C43: 2021-02 | D43: 50000 | F43: 475479 | G43: 110/02管理費撥款電梯專戶 | H43: 管理費撥款
A44: 110.02.04 | B44: 2021-02-04 | C44: 2021-02 | D44: 1605 | F44: 477084 | G44: 存款息 | H44: 存款利息
A45: 110.03.04 | B45: 2021-03-04 | C45: 2021-03 | D45: 1091 | F45: 478175 | G45: 存款息 | H45: 存款利息
A46: 110.03.29 | B46: 2021-03-29 | C46: 2021-03 | D46: 50000 | F46: 528175 | G46: 110/03管理費撥款電梯專戶 | H46: 管理費撥款
... A55: 110.07.27 | B55: 2021-07-27 | C55: 2021-07 | D55: 50000 | F55: 732954 | G55: 110/07管理費撥款電梯專戶 | H55: 管理費撥款
A56: 110.07.27 | B56: 2021-07-27 | C56: 2021-07 | E56: 8000 | F56: 724954 | G56: 支出出席費八月 | H56: 出席費
A57: 110.07.27 | B57: 2021-07-27 | C57: 2021-07 | D57: 8000 | F57: 732954 | G57: 回存出席費八月 | H57: 出席費
A58: 110.08.04 | B58: 2021-08-04 | C58: 2021-08 | D58: 1208 | F58: 734162 | G58: 存款息 | H58: 存款利息
A59: 110.08.27 | B59: 2021-08-27 | C59: 2021-08 | D59: 50000 | F59: 784162 | G59: 110/08管理費撥款電梯專戶 | H59: 管理費撥款
A60: 110.09.06 | B60: 2021-09-06 | C60: 2021-09 | D60: 1208 | F60: 785370 | G60: 存款息 | H60: 存款利息
A61: 110.09.30 | B61: 2021-09-30 | C61: 2021-09 | D61: 50000 | F61: 835370 | G61: 110/09管理費撥款電梯專戶 | H61: 管理費撥款
A62: 110.10.04 | B62: 2021-10-04 | C62: 2021-10 | D62: 1169 | F62: 836539 | G62: 存款息 | H62: 存款利息
A63: 110.10.27 | B63: 2021-10-27 | C63: 2021-10 | D63: 50000 | F63: 886539 | G63: 110/10管理費撥款電梯專戶 | H63: 管理費撥款
A64: 110.11.04 | B64: 2021-11-04 | C64: 2021-11 | D64: 1208 | F64: 887747 | G64: 存款息 | H64: 存款利息
A65: 110.11.29 | B65: 2021-11-29 | C65: 2021-11 | D65: 50000 | F65: 937747 | G65: 110/11管理費撥款電梯專戶 | H65: 管理費撥款
A66: 110.12.06 | B66: 2021-12-06 | C66: 2021-12 | D66: 1169 | F66: 938916 | G66: 存款息 | H66: 存款利息
A67: 110.12.21 | B67: 2021-12-21 | C67: 2021-12 | D67: 40 | F67: 938956 | G67: 存款息 | H67: 存款利息
A68: 110.12.27 | B68: 2021-12-27 | C68: 2021-12 | D68: 50000 | F68: 988956 | G68: 110/12管理費撥款電梯專戶 | H68: 管理費撥款
... A71: 111.02.07 | B71: 2022-02-07 | C71: 2022-02 | D71: 1208 | F71: 1041372 | G71: 存款息 | H71: 存款利息
A72: 111.02.24 | B72: 2022-02-24 | C72: 2022-02 | E72: 378000 | F72: 663372 | G72: 更換主鋼索3 | H72: 主鋼索更換
A73: 111.02.24 | B73: 2022-02-24 | C73: 2022-02 | D73: 50000 | F73: 713372 | G73: 111/02管理費撥款電梯專戶 | H73: 管理費撥款
A74: 111.03.04 | B74: 2022-03-04 | C74: 2022-03 | D74: 1091 | F74: 714463 | G74: 存款息 | H74: 存款利息
A75: 111.03.25 | B75: 2022-03-25 | C75: 2022-03 | D75: 50000 | F75: 764463 | G75: 111/03管理費撥款電梯專戶 | H75: 管理費撥款
A76: 111.04.06 | B76: 2022-04-06 | C76: 2022-04 | D76: 1208 | F76: 765671 | G76: 存款息 | H76: 存款利息
A77: 111.04.25 | B77: 2022-04-25 | C77: 2022-04 | D77: 50000 | F77: 815671 | G77: 111/04管理費撥款電梯專戶 | H77: 管理費撥款
A78: 111.04.25 | B78: 2022-04-25 | C78: 2022-04 | E78: 375900 | F78: 439771 | G78: 支出德懋4月費用 | H78: 管理費代墊
A79: 111.04.25 | B79: 2022-04-25 | C79: 2022-04 | D79: 375900 | F79: 815671 | G79: 回存德懋4月費用 | H79: 管理費代墊
A80: 111.05.04 | B80: 2022-05-04 | C80: 2022-05 | D80: 1169 | F80: 816840 | G80: 存款息 | H80: 存款利息
A81: 111.05.30 | B81: 2022-05-30 | C81: 2022-05 | D81: 50000 | F81: 866840 | G81: 111/05管理費撥款電梯專戶 | H81: 管理費撥款
A82: 111.06.04 | B82: 2022-06-04 | C82: 2022-06 | D82: 1208 | F82: 868048 | G82: 存款息 | H82: 存款利息
A83: 111.06.21 | B83: 2022-06-21 | C83: 2022-06 | D83: 83 | F83: 868131 | G83: 存款息 | H83: 存款利息
A84: 111.06.12 | B84: 2022-06-12 | C84: 2022-06 | D84: 50000 | F84: 918131 | G84: 111/06管理費撥款電梯專戶 | H84: 管理費撥款
A85: 111.07.04 | B85: 2022-07-04 | C85: 2022-07 | D85: 1169 | F85: 919300 | G85: 存款息 | H85: 存款利息
A86: 111.07.27 | B86: 2022-07-27 | C86: 2022-07 | D86: 50000 | F86: 969300 | G86: 111/07管理費撥款電梯專戶 | H86: 管理費撥款
A87: 111.08.04 | B87: 2022-08-04 | C87: 2022-08 | D87: 1208 | F87: 970508 | G87: 存款息 | H87: 存款利息
A88: 111.08.23 | B88: 2022-08-23 | C88: 2022-08 | D88: 50000 | F88: 1020508 | G88: 111/08管理費撥款電梯專戶 | H88: 管理費撥款
A89: 111.09.05 | B89: 2022-09-05 | C89: 2022-09 | D89: 1208 | F89: 1021716 | G89: 存款息 | H89: 存款利息
A90: 111.09.27 | B90: 2022-09-27 | C90: 2022-09 | D90: 50000 | F90: 1071716 | G90: 111/09管理費撥款電梯專戶 | H90: 管理費撥款
... A100: 112.02.04 | B100: 2023-02-04 | C100: 2023-02 | D100: 1208 | F100: 1278796 | G100: 存款息 | H100: 存款利息
A101: 112.02.24 | B101: 2023-02-24 | C101: 2023-02 | E101: 465000 | F101: 813796 | G101: 更換主鋼索2 | H101: 主鋼索更換
A102: 112.02.24 | B102: 2023-02-24 | C102: 2023-02 | D102: 50000 | F102: 863796 | G102: 112/02管理費撥款電梯專戶 | H102: 管理費撥款
A103: 112.03.06 | B103: 2023-03-06 | C103: 2023-03 | D103: 1968 | F103: 865764 | G103: 存款息 | H103: 存款利息
A104: 113.03.28 | B104: 2024-03-28 | C104: 2024-03 | D104: 50000 | F104: 915764 | G104: 112/03管理費撥款電梯專戶 | H104: 管理費撥款
A105: 112.04.06 | B105: 2023-04-06 | C105: 2023-04 | D105: 2178 | F105: 917942 | G105: 存款息 | H105: 存款利息
A106: 112.04.26 | B106: 2023-04-26 | C106: 2023-04 | D106: 50000 | F106: 967942 | G106: 112/04管理費撥款電梯專戶 | H106: 管理費撥款
A107: 112.05.04 | B107: 2023-05-04 | C107: 2023-05 | D107: 2108 | F107: 970050 | G107: 存款息 | H107: 存款利息
A108: 112.05.26 | B108: 2023-05-26 | C108: 2023-05 | D108: 50000 | F108: 1020050 | G108: 112/05管理費撥款電梯專戶 | H108: 管理費撥款
A109: 112.06.05 | B109: 2023-06-05 | C109: 2023-06 | D109: 2178 | F109: 1022228 | G109: 存款息 | H109: 存款利息
A110: 112.06.21 | B110: 2023-06-21 | C110: 2023-06 | D110: 2398 | F110: 1024626 | G110: 存款息 | H110: 存款利息
A111: 112.06.27 | B111: 2023-06-27 | C111: 2023-06 | D111: 50000 | F111: 1074626 | G111: 112/06管理費撥款電梯專戶 | H111: 管理費撥款
A112: 112.07.04 | B112: 2023-07-04 | C112: 2023-07 | D112: 2108 | F112: 1076734 | G112: 存款息 | H112: 存款利息
A113: 112.07.27 | B113: 2023-07-27 | C113: 2023-07 | D113: 50000 | F113: 1126734 | G113: 112/07管理費撥款電梯專戶 | H113: 管理費撥款
... A116: 112.09.04 | B116: 2023-09-04 | C116: 2023-09 | D116: 2178 | F116: 1181090 | G116: 存款息 | H116: 存款利息
A117: 112.09.27 | B117: 2023-09-27 | C117: 2023-09 | E117: 520000 | F117: 661090 | G117: 更換主鋼索8 | H117: 主鋼索更換
A118: 112.09.27 | B118: 2023-09-27 | C118: 2023-09 | D118: 50000 | F118: 711090 | G118: 112/09管理費撥款電梯專戶 | H118: 管理費撥款
A119: 112.10.04 | B119: 2023-10-04 | C119: 2023-10 | D119: 2108 | F119: 713198 | G119: 存款息 | H119: 存款利息
A120: 112.10.25 | B120: 2023-10-25 | C120: 2023-10 | D120: 50000 | F120: 763198 | G120: 112/10管理費撥款電梯專戶 | H120: 管理費撥款
A121: 112.11.06 | B121: 2023-11-06 | C121: 2023-11 | D121: 2178 | F121: 765376 | G121: 存款息 | H121: 存款利息
A122: 112.11.29 | B122: 2023-11-29 | C122: 2023-11 | D122: 50000 | F122: 815376 | G122: 112/11管理費撥款電梯專戶 | H122: 管理費撥款
A123: 112.12.04 | B123: 2023-12-04 | C123: 2023-12 | D123: 2108 | F123: 817484 | G123: 存款息 | H123: 存款利息
A124: 112.12.21 | B124: 2023-12-21 | C124: 2023-12 | D124: 2535 | F124: 820019 | G124: 存款息 | H124: 存款利息
A125: 112.12.27 | B125: 2023-12-27 | C125: 2023-12 | D125: 50000 | F125: 870019 | G125: 112/12管理費撥款電梯專戶 | H125: 管理費撥款
A126: 113.01.04 | B126: 2024-01-04 | C126: 2024-01 | D126: 2178 | F126: 872197 | G126: 存款息 | H126: 存款利息
...

Sheet 電梯專戶月度
A1: 月份 | B1: 收入分析 | E1: 支出分析 | H1: 餘額對照
A2: 月份 | B2: 撥款 (50K/100K) | C2: 利息 | D2: 解定存 | E2: 主鋼索 | F2: 轉定存 | G2: 其他 | H2: 活儲月末 | I2: 整理檔(元大-電梯) | J2: 差額(定存) | K2: 備註
A3: 2019-04 | B3: 50000 | G3: 1250000 | H3: 1300000
A4: 2019-05 | B4: 50000 | H4: 1350000
A5: 2019-06 | B5: 50000 | C5: 129 | H5: 1400129
A6: 2019-07 | B6: 50000 | G6: 100000 | H6: 1550129
A7: 2019-08 | B7: 50000 | H7: 1600129
A8: 2019-09 | B8: 50000 | H8: 1650129
A9: 2019-10 | B9: 50000 | H9: 1700129
A10: 2019-11 | B10: 50000 | H10: 1750129
A11: 2019-12 | B11: 50000 | C11: 410 | H11: 1800539
A12: 2020-01 | B12: 100000 | H12: 1900539
A13: 2020-02 | F13: 1800000 | H13: 100539 | K13: ⚠️ 轉定存
A14: 2020-03 | B14: 50000 | C14: 1502 | H14: 152041
A15: 2020-04 | B15: 50000 | C15: 1605 | H15: 203646
A16: 2020-05 | B16: 50000 | C16: 1553 | H16: 255199
A17: 2020-06 | B17: 50000 | C17: 1733 | H17: 306932
A18: 2020-07 | B18: 50000 | C18: 1553 | H18: 358485
A19: 2020-08 | B19: 50000 | C19: 1605 | H19: 410090
A20: 2020-09 | B20: 50000 | C20: 1605 | H20: 461695
A21: 2020-10 | B21: 50000 | C21: 1553 | E21: 242550 | H21: 270698 | K21: 🔴 主鋼索更換
A22: 2020-11 | B22: 50000 | C22: 1605 | H22: 322303
A23: 2020-12 | B23: 50000 | C23: 1571 | H23: 373874
A24: 2021-01 | B24: 50000 | C24: 1605 | H24: 425479 | I24: 2225479 | J24: 1800000
A25: 2021-02 | B25: 50000 | C25: 1605 | H25: 477084 | I25: 2277084 | J25: 1800000
A26: 2021-03 | B26: 50000 | C26: 1091 | H26: 528175 | I26: 2328175 | J26: 1800000
A27: 2021-04 | B27: 50000 | C27: 1208 | H27: 579383 | I27: 2379383 | J27: 1800000
A28: 2021-05 | B28: 50000 | C28: 1169 | H28: 630552 | I28: 2430552 | J28: 1800000
A29: 2021-06 | B29: 50000 | C29: 1233 | H29: 681785 | I29: 2481785 | J29: 1800000
A30: 2021-07 | B30: 50000 | C30: 1169 | H30: 732954 | I30: 2532954 | J30: 1800000
A31: 2021-08 | B31: 50000 | C31: 1208 | H31: 784162 | I31: 2584162 | J31: 1800000
A32: 2021-09 | B32: 50000 | C32: 1208 | H32: 835370 | I32: 2635370 | J32: 1800000
A33: 2021-10 | B33: 50000 | C33: 1169 | H33: 886539 | I33: 2686539 | J33: 1800000
A34: 2021-11 | B34: 50000 | C34: 1208 | H34: 937747 | I34: 2737747 | J34: 1800000
A35: 2021-12 | B35: 50000 | C35: 1209 | H35: 988956 | I35: 2788956 | J35: 1800000
A36: 2022-01 | B36: 50000 | C36: 1208 | H36: 1040164 | I36: 2840164 | J36: 1800000
A37: 2022-02 | B37: 50000 | C37: 1208 | E37: 378000 | H37: 713372 | I37: 2513372 | J37: 1800000 | K37: 🔴 主鋼索更換
A38: 2022-03 | B38: 50000 | C38: 1091 | H38: 764463 | I38: 2564463 | J38: 1800000
A39: 2022-04 | B39: 50000 | C39: 1208 | H39: 815671 | I39: 2615671 | J39: 1800000
A40: 2022-05 | B40: 50000 | C40: 1169 | H40: 866840 | I40: 2666840 | J40: 1800000
A41: 2022-06 | B41: 50000 | C41: 1291 | H41: 918131 | I41: 2718131 | J41: 1800000
A42: 2022-07 | B42: 50000 | C42: 1169 | H42: 969300 | I42: 2769300 | J42: 1800000
A43: 2022-08 | B43: 50000 | C43: 1208 | H43: 1020508 | I43: 2820508 | J43: 1800000
A44: 2022-09 | B44: 50000 | C44: 1208 | H44: 1071716 | I44: 2871716 | J44: 1800000
A45: 2022-10 | B45: 50000 | C45: 1169 | H45: 1122885 | I45: 2922885 | J45: 1800000
A46: 2022-11 | B46: 50000 | C46: 1208 | H46: 1174093 | I46: 2974093 | J46: 1800000
A47: 2022-12 | B47: 50000 | C47: 2287 | H47: 1226380 | I47: 3026380 | J47: 1800000
A48: 2023-01 | B48: 50000 | C48: 1208 | H48: 1277588 | I48: 3077588 | J48: 1800000
A49: 2023-02 | B49: 50000 | C49: 1208 | E49: 465000 | H49: 863796 | I49: 2663796 | J49: 1800000 | K49: 🔴 主鋼索更換
A50: 2023-03 | C50: 1968 | H50: 865764 | I50: 2715764 | J50: 1850000
A51: 2023-04 | B51: 50000 | C51: 2178 | H51: 967942 | I51: 2767942 | J51: 1800000
A52: 2023-05 | B52: 50000 | C52: 2108 | H52: 1020050 | I52: 2820050 | J52: 1800000
A53: 2023-06 | B53: 50000 | C53: 4576 | H53: 1074626 | I53: 2874626 | J53: 1800000
A54: 2023-07 | B54: 50000 | C54: 2108 | H54: 1126734 | I54: 2926734 | J54: 1800000
A55: 2023-08 | B55: 50000 | C55: 2178 | H55: 1178912 | I55: 2978912 | J55: 1800000
A56: 2023-09 | B56: 50000 | C56: 2178 | E56: 520000 | H56: 711090 | I56: 2511090 | J56: 1800000 | K56: 🔴 主鋼索更換
A57: 2023-10 | B57: 50000 | C57: 2108 | H57: 763198 | I57: 2563198 | J57: 1800000
A58: 2023-11 | B58: 50000 | C58: 2178 | H58: 815376 | I58: 2615376 | J58: 1800000
A59: 2023-12 | B59: 50000 | C59: 4643 | H59: 870019 | I59: 2670019 | J59: 1800000
A60: 2024-01 | B60: 50000 | C60: 2178 | H60: 922197 | I60: 2722197 | J60: 1800000
A61: 2024-02 | B61: 50000 | C61: 2178 | E61: 520000 | H61: 454375 | I61: 2254375 | J61: 1800000 | K61: 🔴 主鋼索更換
A62: 2024-03 | B62: 100000 | C62: 2217 | H62: 506592 | I62: 2306592 | J62: 1800000
A63: 2024-04 | B63: 50000 | C63: 2370 | H63: 558962 | I63: 2358962 | J63: 1800000
A64: 2024-05 | B64: 50000 | C64: 2293 | H64: 611255 | I64: 2411255 | J64: 1800000
A65: 2024-06 | B65: 50000 | C65: 4293 | H65: 665548 | I65: 2465548 | J65: 1800000
A66: 2024-07 | B66: 50000 | C66: 2293 | H66: 717841 | I66: 2517841 | J66: 1800000
A67: 2024-08 | B67: 50000 | C67: 2370 | H67: 770211 | I67: 2570211 | J67: 1800000
A68: 2024-09 | B68: 50000 | C68: 2370 | H68: 822581 | I68: 2622581 | J68: 1800000
A69: 2024-10 | B69: 50000 | C69: 2293 | E69: 520000 | H69: 354874 | K69: 🔴 主鋼索更換 整理檔缺漏月份
A70: 2024-11 | C70: 2370 | H70: 357244 | I70: 2209537 | J70: 1852293
A71: 2024-12 | B71: 50000 | C71: 4359 | H71: 411603 | I71: 2213973 | J71: 1802370
A72: 2025-01 | B72: 100000 | C72: 2370 | H72: 513973 | I72: 2313973 | J72: 1800000
A73: 2025-02 | C73: 2370 | H73: 516343 | I73: 2368656 | J73: 1852313
A74: 2025-03 | B74: 50000 | C74: 2313 | H74: 568656 | K74: 整理檔缺漏月份
A75: 2025-04 | B75: 50000 | C75: 2561 | H75: 621217 | I75: 2421217 | J75: 1800000
A76: 2025-05 | B76: 50000 | D76: 1799331 | E76: 1560000 | H76: 910548 | I76: 910548 | J76: 0 | K76: 🔴 主鋼索更換 ✅ 解定存
A77: 2025-06 | C77: 2049 | H77: 912597 | I77: 912597 | J77: 0
A78: 2025-07 | B78: 200000 | E78: 520000 | H78: 592597 | I78: 912597 | J78: 320000 | K78: 🔴 主鋼索更換
A79: 2025-08 | B79: 100000 | G79: -50000 | H79: 642597 | K79: 整理檔缺漏月份
A80: 2025-09 | B80: 100000 | H80: 742597 | K80: 整理檔缺漏月份
A81: 2025-10 | B81: 100000 | H81: 842597 | K81: 整理檔缺漏月份
A82: 2025-11 | B82: 100000 | H82: 942597 | K82: 整理檔缺漏月份
A83: 2025-12 | B83: 100000 | C83: 2654 | H83: 1045251 | K83: 整理檔缺漏月份
A84: 2026-01 | B84: 100000 | H84: 1145251 | K84: 整理檔缺漏月份
A85: 2026-02 | B85: 100000 | H85: 1245251 | K85: 整理檔缺漏月份
A86: 2026-03 | B86: 100000 | H86: 1345251 | K86: 整理檔缺漏月份
A87: 全期合計 | B87: 4650000 | C87: 121470 | D87: 1799331 | E87: 4725550 | F87: 1800000 | G87: 1300000

Sheet 議案-游泳池
A1: 議案彙整 — 游泳池
A2: 泳池機房保養 + 設備修繕 + 周邊用品 (含分項抽出，避免高估)
A4: ─── 統計 ───
A5: 合計金額 (NT$) | B5: 698790
A6: 筆數 | B6: 44
A7: 期間 | B7: 2021-01 ~ 2025-12
A9: ─── 各年度 ───
A10: 年度 | B10: 泳池支出 (NT$)
A11: 2021 年 | B11: 74700
A12: 2022 年 | B12: 21000
A13: 2023 年 | B13: 161730
A14: 2024 年 | B14: 193460
A15: 2025 年 | B15: 247900
A17: ─── 明細 (每筆顯示原始全額 + 抽出後 pool-only 金額) ───
A18: 月份 | B18: 原始全額 (NT$) | C18: Pool-only (NT$) | D18: 工程項目 | E18: 備註
A19: 2021-01 | B19: 3000 | C19: 3000 | D19: 侑昇-泳池機房保養(109/12) | E19: 機房保養 100%
A20: 2021-02 | B20: 3000 | C20: 3000 | D20: 侑昇-泳池機房保養(110/02) | E20: 機房保養
A21: 2021-02 | B21: 3000 | C21: 3000 | D21: 侑昇-泳池機房保養(110/01) | E21: 機房保養 (1+2月補繳)
A22: 2021-03 | B22: 3000 | C22: 3000 | D22: 侑昇-泳池機房保養(110/03) | E22: 機房保養
A23: 2021-04 | B23: 3000 | C23: 3000 | D23: 侑昇-泳池機房保養(110/04) | E23: 機房保養
A24: 2021-05 | B24: 0 | C24: 0 | D24: 侑昇-泳池機房保養(110/05) | E24: 排水閥故障未保養
A25: 2021-06 | B25: 0 | C25: 0 | D25: 侑昇-泳池機房保養(110/06) | E25: 合約7月開始
A26: 2021-07 | B26: 3500 | C26: 3500 | D26: 侑昇-泳池機房保養(110/07) | E26: 機房保養 (新合約3,500/月)
A27: 2021-07 | B27: 70900 | C27: 36050 | D27: 鑫禾機電 …泳池設備修繕$36,050… | E27: 只計 泳池設備修繕 $36,050
A28: 2021-08 | B28: 3500 | C28: 3500 | D28: 侑昇-泳池機房保養(110/08) | E28: 機房保養
A29: 2021-09 | B29: 3500 | C29: 3500 | D29: 侑昇-泳池機房保養(110/09) | E29: 機房保養
A30: 2021-10 | B30: 3500 | C30: 3500 | D30: 侑昇-泳池機房保養(110/10) | E30: 機房保養
... A62: 2025-12 | B62: 4517 | C62: 4517 | D62: 購買游泳池陽傘、救生員座椅(七月) | E62: 100%
A63: 合計 | B63: 808940 | C63: 698790
A65: ─── 門票收入 vs 游泳池支出 對比 ───
A67: 年度 | B67: 門票收入 (NT$) | C67: 游泳池支出 (NT$) | D67: 赤字 (NT$) | E67: 收入抵支出 %
A68: 2021 年 | B68: 0 | C68: 74700 | D68: -74700 | E68: 0.0%
A69: 2022 年 | B69: 0 | C69: 21000 | D69: -21000 | E69: 0.0%
A70: 2023 年 | B70: 49650 | C70: 161730 | D70: -112080 | E70: 30.7%
A71: 2024 年 | B71: 52230 | C71: 193460 | D71: -141230 | E71: 27.0%
A72: 2025 年 | B72: 74060 | C72: 247900 | D72: -173840 | E72: 29.9%
A73: 合計 | B73: 175940 | C73: 698790 | D73: -522850 | E73: 25.2%
A75: 註：泳卷收入 / 泳池收入 已於 收入明細 sheet 統一改稱「門票收入」
A76: 註：游泳池支出 = 議案-游泳池 sheet 上方各年度 (機房保養 + 設備修繕 + 救生員 + 周邊用品 — pool-only)

Sheet 公共電費
A1: 月份 | B1: 公共電費 | C1: 說明
A2: 2021-01 | B2: 87413 | C2: 109年12月公共電費: 87,413
A3: 2021-02 | B3: 88215 | C3: 公共電費(109.12.11至110.01.12): 88,215
A4: 2021-03 | B4: 101777 | C4: 公共電費(110.01.13至110.2.16): 101,777
A5: 2021-04 | B5: 85178 | C5: 公共電費(110.02.17至110.03.15): 85,178
A6: 2021-05 | B6: 84824 | C6: 公共電費(110.03.17至110.04.14): 84,824
A7: 2021-06 | B7: 88643 | C7: 公共電費(110.04.16至110.05.15): 88,643
A8: 2021-07 | B8: 89266 | C8: 公共電費(110.05.17至110.06.15): 89,266
A9: 2021-08 | B9: 88231 | C9: 公共電費(110.05.17至110.06.15): 88,231
A10: 2021-09 | B10: 80066 | C10: 公共電費(110.07.13至110.08.10): 80,066
A11: 2021-10 | B11: 95341 | C11: 公共電費: 95,341
A12: 2021-11 | B12: 104138 | C12: 公共電費(110.09.10~110.12.05): 104,138
A13: 2021-12 | B13: 71935 | C13: 公共電費: 71,935
... A65: 2026-04 | B65: 92257 | C65: ◆公共電費: 92,257
A67: ─ 統計 ─
A68: 期間合計 | B68: 6431546
A69: 月均 | B69: 100492.91
A70: 中位 | B70: 97375
A71: 最高 | B71: 227933
A72: 最低 | B72: 0
A74: ─ 年度小計 ─
A75: 2021 年 | B75: 1065027
A76: 2022 年 | B76: 1183450
A77: 2023 年 | B77: 1137916
A78: 2024 年 | B78: 1510829
A79: 2025 年 | B79: 1182049
A80: 2026 年 | B80: 352275
A82: ─ 季度小計 ─
A83: 2021-Q1 | B83: 277405
A84: 2021-Q2 | B84: 258645
A85: 2021-Q3 | B85: 257563
A86: 2021-Q4 | B86: 271414
A87: 2022-Q1 | B87: 274545
A88: 2022-Q2 | B88: 265067
A89: 2022-Q3 | B89: 325650
A90: 2022-Q4 | B90: 318188
A91: 2023-Q1 | B91: 265354
A92: 2023-Q2 | B92: 262411
A93: 2023-Q3 | B93: 312400
A94: 2023-Q4 | B94: 297751
... A104: 2026-Q2 | B104: 92257
